Workbook

Sheet Overview
A1: Lab 8 — Product Lifecycle & Portfolio Intelligence
A2: Merged project tracker · Figures on this tab are formulas and update as the other tabs change.
A4: Project at a glance
A5: Project | B5: Acies AgenticBus — Lab 8: Product Lifecycle & Portfolio Intelligence
A6: Purpose, as we understand it | B6: A GTM demo asset that opens VP-level conversations with FMCG companies. Awaiting confirmation — Q1.
A7: Opening problem | B7: Slow decisions, poor product profitability visibility, missed rationalization opportunities, and disconnected market/customer signals.
A8: Primary persona | B8: VP Product Management / VP Portfolio Strategy
A9: Secondary personas | B9: Product Manager; Pricing & Margin Partner
A10: Previous team | B10: Amita, SreeVyshnavi, acies-Jai, Jaiadithya A — 369 commits, 18 May – 27 Jul 2026
A11: Project start | B11: 3 Sep 2026 (per team tracker)
A12: Deadline | B12: Not set (confirmed 22 Sep). The team tracker's 20 working days from 3 Sep is a placeholder. See Q9.
A13: Current team | B13: Guna
A14: Programme owner
A15: Live demo | B15: ilp-ppl-dash-board.vercel.app
A16: Tracker as of | B16: =TODAY()
A18: Scope (team's problem understanding)
A19: In scope | B19: Portfolio health; launch readiness; product/SKU profitability; SKU rationalization; market/competitor/VoC signals; portfolio/product KPIs.
A20: Out of scope | B20: Full PLM engineering system; CAD; R&D/technical product development workflows; marketing campaign execution for launches.
A22: Gates — earliest dates at planned durations
A23: Gate 1 — End of SPS | B23: ='Project Plan'!$O$14 | C23: ='Project Plan'!$L$14
A24: Gate 2 — Solution design complete | B24: ='Project Plan'!$O$23 | C24: ='Project Plan'!$L$23
A25: Gate 3 — Functional prototype — five tabs without AI | B25: ='Project Plan'!$O$37 | C25: ='Project Plan'!$L$37
A26: Gate 4 — Final demo | B26: ='Project Plan'!$O$45 | C26: ='Project Plan'!$L$45
A27: Working days from today to Gate 4 | B27: =IF(C26="","",NETWORKDAYS(TODAY(),C26))
A29: Status
A30: Activities in plan | B30: =COUNTIF('Project Plan'!$C$5:$C$46,"Activity")
A31: Done | B31: =COUNTIFS('Project Plan'!$C$5:$C$46,"Activity",'Project Plan'!$I$5:$I$46,"Done")
A32: In progress | B32: =COUNTIFS('Project Plan'!$C$5:$C$46,"Activity",'Project Plan'!$I$5:$I$46,"In progress")
A33: Rework needed | B33: =COUNTIFS('Project Plan'!$C$5:$C$46,"Activity",'Project Plan'!$I$5:$I$46,"Rework needed")
A34: Not started | B34: =COUNTIFS('Project Plan'!$C$5:$C$46,"Activity",'Project Plan'!$I$5:$I$46,"Not started")
A35: Blocked or at risk | B35: =COUNTIFS('Project Plan'!$C$5:$C$46,"Activity",'Project Plan'!$I$5:$I$46,"Blocked")+COUNTIFS('Project Plan'!$C$5:$C$46,"Activity",'Project Plan'!$I$5:$I$46,"At risk")
A36: Tab-rework activities still needing an estimate (3.2–3.6) | B36: =COUNTBLANK('Project Plan'!$J$29:$J$33)
A37: Activities with no owner yet | B37: =COUNTIFS('Project Plan'!$C$5:$C$46,"Activity",'Project Plan'!$H$5:$H$46,"")
A38: Open questions | B38: =COUNTIF('Open Questions'!$J$5:$J$19,"Open")
A39: Questions answered or defaulted | B39: =COUNTIF('Open Questions'!$J$5:$J$19,"Answered")+COUNTIF('Open Questions'!$J$5:$J$19,"Defaulted")
A40: High-severity risks and issues not closed | B40: =COUNTIFS('Risks & Issues'!$G$5:$G$25,"High",'Risks & Issues'!$K$5:$K$25,"<>Closed")
A41: Stakeholder meetings held | B41: =COUNTIF('Stakeholder Meetings'!$I$5:$I$12,"Held")&" of "&COUNTA('Stakeholder Meetings'!$A$5:$A$12)
A42: Gap-analysis items | B42: =COUNTA('Gap Analysis'!$A$5:$A$48)
A44: Headlines
A45: • | B45: The database is live and reconciles to the source figures. The application does not read it yet — Backend (3.8) and Integration (3.9).
A46: • | B46: The team's functional review found 44 gaps across Portfolio Health, Launch Readiness and cross-module flow — including a revenue figure about 22× too high, now confirmed as a bug.
A47: • | B47: Five plans were in circulation. This tracker merges them; M8 should adopt it and retire the rest.
A48: • | B48: No deadline is set. Gate 4 above is the earliest date at the plan's durations, and it is optimistic: tab rework (3.2–3.6) has no estimates yet.
A49: • | B49: TODO.md (the dev-level tracker, separate from this Project Plan) stood at 30 Sep 2026: 12 of 17 tracked phases Done, 2 partly done, 2 open, 1 decided (~71%). By checkbox count 19/53 (~36%) — lower because most completed phases (schema, dataset generation, the database, branding) were logged as narrative/tables rather than checkboxes, while nearly all remaining open work is checkbox-tracked, so the checkbox ratio understates progress.
A51: What this tracker replaces
A52: • | B52: The 16-phase plan (screenshot) — including a 'Core CRM Modules' row that does not apply to this product.
A53: • | B53: The team tracker's Project Tracker, Project Internal Tracker and Action Plan tabs — their content is merged here.
A54: • | B54: The first version of this tracker.
A56: Tabs
A57: Project Plan | B57: P0–P4 with Gates 1–4. Owner, status, dates, dependencies, definition of done. Source column shows where each row came from.
A58: Open Questions | B58: The 15 decisions we need, each with a recommendation and a default.
A59: Stakeholder Meetings | B59: Meetings M1–M8 and the questions each settles.
A60: Gap Analysis | B60: The team's 44 functional gaps, each mapped to a plan step.
A61: Personas & Journey | B61: Who needs what; current → future journey; the end-to-end decision journey.
A62: Risks & Issues | B62: What could go wrong or already has, with severity.
A63: Decisions | B63: Decisions made, why, and when to revisit.
A64: Architecture Roadmap | B64: How we get from today's architecture to the target.
A65: Research & Data | B65: Our research and the team's; the dataset we built and its gaps.
A66: Handover Findings | B66: The condition of what we received — the reverse-KT agenda.
A67: Timeline | B67: What happened and when.
A68: Benchmark | B68: The team's PLM vendor comparison, with caveats.
A69: Links | B69: Every document, repository and the live demo.
A71: Legend
A72: Light-yellow cell | B72: Please fill in or confirm — including role names to replace with people
A73: Blue text | B73: Typed input — dates and durations you can change
A74: Black text | B74: Formula or fixed text — do not overwrite formulas
A75: Grey italic date | B75: Tentative — computed from durations; moves when an input changes
A76: Shaded row | B76: A gate — its date is the latest end of the activities before it

Sheet Project Plan
A1: Project Plan — merged
A2: Backbone: the team tracker's P1–P4 phases and Gates 1–4. Our workstreams merged in and marked by source. Blue = typed input · black = formula · light yellow = please fill in · grey italic = tentative date.
A4: ID | B4: Phase | C4: Type | D4: Activity | E4: Source | F4: Objective | G4: Key question | H4: Owner | I4: Status | J4: Days (working) | K4: Start | L4: End | M4: Date basis | N4: Depends on | O4: Expected outcome / definition of done | P4: Where it actually stands | Q4: Evidence
A5: 0.1 | B5: P0 · Handover & remediation | C5: Activity | D5: Knowledge transfer (KT) and reverse KT | E5: Original 16-phase plan | F5: Receive the existing application from the previous team, then play our understanding back. | G5: Have we understood the product, its data and its personas the way the previous team intended? | I5: In progress | J5: 5 | L5: =IF(OR(K5="",J5=""),"",WORKDAY(K5,J5-1)) | M5: To confirm | N5: — | O5: RKT held; previous team confirms our understanding; handover gaps logged. | P5: KT completed before the first commit on 1 Sep. RKT not yet held — Handover Findings is its agenda (meeting M5). | Q5: Handover Findings tab
A6: 0.2 | B6: P0 · Handover & remediation | C6: Activity | D6: Codebase remediation | E6: Added | F6: Make the inherited code safe to change before building on it. | G6: Can we change the code without breaking what already works? | H6: Guna | I6: Done | J6: =IF(OR(K6="",L6=""),"",NETWORKDAYS(K6,L6)) | K6: 46266 | L6: 46285 | M6: Actual (git) | N6: 0.1 | O6: Type check and build clean; 27/27 smoke; no debris in the repository root. | P6: 187 files removed; nine files of 22,619 lines split into 30 modules (−47%); 1,237 invalid colour classes fixed; dead Express server and 124 unused npm packages removed. | Q6: Commits 1–20 Sep; TODO.md
A7: 1.1 | B7: P1 · Business Understanding & SPS | C7: Activity | D7: Understand current problem statement | E7: Team tracker | F7: Understand the business problem, scope, personas, expected outcomes and terminology in the brief. | G7: What problem are we solving? Who is affected? What is explicitly in/out of scope? | H7: Team Lead | I7: In progress | J7: =IF(OR(K7="",L7=""),"",NETWORKDAYS(K7,L7)) | K7: 46268 | L7: =L13 | M7: Start per team tracker; ends at stakeholder sign-off | N7: — | O7: Initial problem understanding; agreed terminology; open questions | P7: Problem, personas and scope written up (Overview → Scope). Four problem areas still need ranking — Q14. | Q7: Team tracker; pitch.md
A8: 1.2 | B8: P1 · Business Understanding & SPS | C8: Activity | D8: Map current-state problem | E8: Team tracker | F8: Translate the stated problem into a current-state process and identify where delays/manual work occur. | G8: Where does data come from? Where are decisions delayed? Where are workarounds used? | H8: Business Analyst | I8: In progress | J8: =IF(OR(K8="",L8=""),"",NETWORKDAYS(K8,L8)) | L8: =L13 | M8: Tentative — ends at stakeholder sign-off | N8: — | O8: As-Is process map + pain-point map | P8: Current → future decision journey drafted, plus an end-to-end journey in Miro. Pain points listed but not yet validated. | Q8: Personas & Journey tab
A9: 1.3 | B9: P1 · Business Understanding & SPS | C9: Activity | D9: Identify and validate personas | E9: Team tracker | F9: Understand the needs of VP Product Management, Product Manager and Pricing/Margin Partner. | G9: What does each persona decide? What information does each need? | H9: Business Analyst | I9: Done | J9: =IF(OR(K9="",L9=""),"",NETWORKDAYS(K9,L9)) | L9: =L13 | M9: Tentative — ends at stakeholder sign-off | N9: 1.7 | O9: Persona + decision + KPI matrix | P9: Persona x capability matrix validated at the code level: a tab-by-tab audit ('Nine Tabs, Zero Backend', 23 Sep) confirmed only the VP has a dedicated view anywhere, and found Product Manager -- marked primary on Launch Readiness -- is silently routed into the VP's own screen. A working prototype now reorders the sidebar per role from this same matrix, verified on all three roles. Both are evidence for M3, not yet signed off (Q7). | Q9: Personas & Journey tab; Report 2
A10: 1.4 | B10: P1 · Business Understanding & SPS | C10: Activity | D10: Build diagnostic issue tree | E10: Team tracker | F10: Break the broad portfolio problem into measurable problem areas and hypotheses. | G10: What are the possible root causes behind slow launches, poor profitability, rationalization gaps and disconnected signals? | H10: Business Analyst | I10: Not started | J10: 2 | K10: 46288 | L10: =IF(OR(K10="",J10=""),"",WORKDAY(K10,J10-1)) | M10: Tentative — our estimate | N10: — | O10: Issue tree + hypotheses | P10: Not started. Handover Findings covers code-level causes; business root causes are still hypotheses. | Q10: —
A11: 1.5 | B11: P1 · Business Understanding & SPS | C11: Activity | D11: Secondary research | E11: Team tracker | F11: Research portfolio management, SKU rationalization, launch readiness, profitability and AI applications. | G11: What industry practices and benchmarks can validate/refine the problem? | H11: Research Owner | I11: Done | J11: =IF(OR(K11="",L11=""),"",NETWORKDAYS(K11,L11)) | L11: 46282 | M11: Actual end | N11: — | O11: Research notes + evidence | P11: Report 3 (FMCG intelligence vendors) and the team's PLM benchmark cover it between them. | Q11: Report 3; Benchmark tab
A12: 1.6 | B12: P1 · Business Understanding & SPS | C12: Activity | D12: SPS synthesis | E12: Team tracker | F12: Convert research and stakeholder findings into an evidence-backed problem statement. | G12: What is the specific root cause? Which pain point is most important? | H12: Team Lead | I12: Not started | J12: 1 | K12: =WORKDAY(MAX(L10,L13),1) | L12: =IF(OR(K12="",J12=""),"",WORKDAY(K12,J12-1)) | M12: Tentative — our estimate | N12: 1.4, 1.7 | O12: SPS findings + validated problem statement | P12: Waits on stakeholder answers. | Q12: —
A13: 1.7 | B13: P1 · Business Understanding & SPS | C13: Activity | D13: Stakeholder alignment on scope (M1–M4) | E13: Added | F13: Settle scope, metrics, tabs and delivery with the people who own them. | G13: Is this a demo asset or a product, and what does the brief really require? | I13: Not started | J13: 4 | K13: 46288 | L13: =IF(OR(K13="",J13=""),"",WORKDAY(K13,J13-1)) | M13: Tentative | N13: — | O13: M1–M4 held; every open question answered or defaulted. | P13: Not yet scheduled. Every tentative date after this row assumes it finishes on the date shown. | Q13: Stakeholder Meetings tab
A14: G1 | B14: P1 · Business Understanding & SPS | C14: Gate | D14: Gate 1 — End of SPS | E14: Team tracker | F14: Validated problem + issue tree + personas + research findings | G14: — | I14: Not started | L14: =L12 | M14: Tentative | N14: 1.1–1.7 | O14: Validated problem + issue tree + personas + research findings | P14: — | Q14: —
A15: 2.1 | B15: P2 · Solution Definition | C15: Activity | D15: Define decision journeys | E15: Team tracker | F15: Define the decisions the solution should support from the perspective of each persona. | G15: What decision should the user make after seeing the insight? | H15: Business Analyst | I15: In progress | J15: 1 | K15: =WORKDAY(L14,1) | L15: =IF(OR(K15="",J15=""),"",WORKDAY(K15,J15-1)) | M15: Tentative — our estimate | N15: G1 | O15: Decision journey map | P15: Draft exists (Miro journey). Missing: the closed loop from decision to measured impact. | Q15: Personas & Journey tab
A16: 2.2 | B16: P2 · Solution Definition | C16: Activity | D16: Define five functional modules | E16: Team tracker | F16: Translate the brief into the five required domain modules and their business questions. | G16: What should each tab show and what decision does it enable? | H16: Product Owner | I16: In progress | J16: 1 | K16: =WORKDAY(L14,1) | L16: =IF(OR(K16="",J16=""),"",WORKDAY(K16,J16-1)) | M16: Tentative — our estimate | N16: G1, Q7 | O16: Module requirements matrix | P16: Report 2 recommends the brief's five modules; sign-off pending (Q7). | Q16: Report 2
A17: 2.3 | B17: P2 · Solution Definition | C17: Activity | D17: Define KPI framework | E17: Team tracker | F17: Define KPI meaning, calculation approach, grain, source and target/benchmark assumptions. | G17: How will Margin, Time-to-Market, Launch Success, SKU Productivity, Complexity and Cannibalization be measured? | H17: Analytics Lead | I17: In progress | J17: 2 | K17: =WORKDAY(L14,1) | L17: =IF(OR(K17="",J17=""),"",WORKDAY(K17,J17-1)) | M17: Tentative — our estimate | N17: G1, Q2–Q5 | O17: KPI dictionary | P17: Report 1 defines every metric. Open: the revenue baseline (Q2); two KPIs with no data (Q3); unsupported cards (Q4, Q5). | Q17: Report 1
A18: 2.4 | B18: P2 · Solution Definition | C18: Activity | D18: Define data requirements | E18: Team tracker | F18: Identify product, sales, cost, supply, launch, market, customer and competitor data needed. | G18: What fields, granularity and refresh frequency are required? | H18: Guna | I18: Done | J18: =IF(OR(K18="",L18=""),"",NETWORKDAYS(K18,L18)) | L18: 46279 | M18: Actual end | N18: — | O18: Data requirement matrix | P18: 13-table star schema specified with types and keys. | Q18: data_model_specification.md
A19: 2.5 | B19: P2 · Solution Definition | C19: Activity | D19: Define business rules | E19: Team tracker | F19: Create transparent decision logic for readiness, profitability alerts and rationalization. | G19: What conditions trigger GO/REVIEW/DELAY or retain/grow/bundle/reposition/sunset? | H19: Analytics Lead | I19: Not started | J19: 2 | K19: =WORKDAY(L17,1) | L19: =IF(OR(K19="",J19=""),"",WORKDAY(K19,J19-1)) | M19: Tentative — our estimate | N19: 2.3, Q13 | O19: Business rule catalogue | P19: Blocked until one decision vocabulary is agreed (Q13). | Q19: —
A20: 2.6 | B20: P2 · Solution Definition | C20: Activity | D20: Define Now vs AI-Assisted vs Agentic | E20: Team tracker | F20: Define where automation, AI assistance and agent orchestration add value. | G20: What should remain human-led? What can AI analyze? What can agents monitor/recommend? | H20: AI Lead | I20: In progress | J20: 1 | K20: =WORKDAY(L14,1) | L20: =IF(OR(K20="",J20=""),"",WORKDAY(K20,J20-1)) | M20: Tentative — our estimate | N20: G1 | O20: AI/Agentic evolution map | P20: Now / Next / Future architecture drawn; the rule 'the LLM explains, never computes' is proposed (Q10). | Q20: system_architecture.md
A21: 2.7 | B21: P2 · Solution Definition | C21: Activity | D21: Solution architecture and hosting | E21: Original 16-phase plan | F21: Agree the technical architecture and where each part runs. | G21: What runs where, and what does it cost? | I21: In progress | J21: 2 | K21: =WORKDAY(L14,1) | L21: =IF(OR(K21="",J21=""),"",WORKDAY(K21,J21-1)) | M21: Tentative — original plan (0.3 week) | N21: G1, Q10 | O21: Target architecture and hosting agreed. | P21: Stack decided: PostgreSQL, Python / FastAPI, metrics in SQL. Hosting and LLM budget open (Q10). | Q21: Architecture Roadmap tab
A22: 2.8 | B22: P2 · Solution Definition | C22: Activity | D22: UI/UX design for the five domain tabs | E22: Original 16-phase plan | F22: Lay out the five domain tabs for each persona, using the gap analyses as requirements. | G22: Does each tab lead its persona from insight to decision? | I22: Not started | J22: 3 | K22: =WORKDAY(L16,1) | L22: =IF(OR(K22="",J22=""),"",WORKDAY(K22,J22-1)) | M22: Tentative — original plan (3 days) | N22: 2.2 | O22: Approved layouts for five tabs × three personas. | P22: The design system exists; this is consolidation, not a fresh visual design. A first prototype (persona-ordered sidebar, App.tsx) is built and verified but not committed -- draft input for this step, not a substitute for it. | Q22: Gap Analysis tab
A23: G2 | B23: P2 · Solution Definition | C23: Gate | D23: Gate 2 — Solution design complete | E23: Team tracker | F23: Five modules + KPI dictionary + data model + business rules | G23: — | I23: Not started | L23: =MAX(L15,L16,L17,L19,L20,L21,L22) | M23: Tentative | N23: 2.1–2.8 | O23: Five modules + KPI dictionary + data model + business rules | P23: — | Q23: —
A24: 3.1 | B24: P3 · Data & Prototype | C24: Activity | D24: Create simulated data model | E24: Team tracker | F24: Create realistic linked datasets for products/SKUs, sales, costs, supply, launches, market and VoC. | G24: Can the data support every required module and KPI? | H24: Guna | I24: Done | J24: =IF(OR(K24="",L24=""),"",NETWORKDAYS(K24,L24)) | K24: 46274 | L24: 46279 | M24: Approx. start (seed date); actual end | N24: — | O24: Validated prototype dataset | P24: 119 SKUs × 7 countries × 4 channels × 731 days; 368,013 fact rows; 16 of 16 validation targets met. | Q24: Research & Data tab
A25: 3.1a | B25: P3 · Data & Prototype | C25: Activity | D25: Load the PostgreSQL warehouse | E25: Added | F25: Put the dataset into a real database the application can read. | G25: Do the loaded totals reconcile? | H25: Guna | I25: Done | J25: =IF(OR(K25="",L25=""),"",NETWORKDAYS(K25,L25)) | K25: 46279 | L25: 46285 | M25: Actual | N25: 3.1 | O25: 13 tables loaded; totals match the generator. | P25: 377,364 rows loaded 20 Sep. Reconciles: $473.0M net sales, +8.29% growth, 38.55% margin. | Q25: data/schema/
A26: 3.1b | B26: P3 · Data & Prototype | C26: Activity | D26: Derived-metric SQL and SQL validation | E26: Added | F26: Give every formula a single implementation, in SQL. | G26: Do the 16 checks pass in SQL too? | I26: Not started | J26: 2 | K26: =WORKDAY(L17,1) | L26: =IF(OR(K26="",J26=""),"",WORKDAY(K26,J26-1)) | M26: Tentative — our estimate | N26: 3.1a, Q2 | O26: Derived tables rebuilt in SQL; 16 checks pass in SQL. | P26: 03_derive_metrics.sql and 04_validate.sql. | Q26: TODO.md O2
A27: 3.1c | B27: P3 · Data & Prototype | C27: Activity | D27: Metric integrity and data wiring | E27: Added | F27: One value per metric on every screen. | G27: Does any figure disagree between screens? | I27: In progress | J27: 5 | K27: =WORKDAY(L17,1) | L27: =IF(OR(K27="",J27=""),"",WORKDAY(K27,J27-1)) | M27: Tentative — our estimate | N27: 2.3, Q2, Q4, Q5 | O27: Each metric has one value everywhere; no empty KPI strip; lifecycle revenue bug fixed. | P27: Every formula in the app catalogued and verified against source (documentation/formulas.md, 23 Sep) -- Python generator, SQL, and all 9 tabs, each marked real / real-formula-fake-input / fabricated. New finding: the timeline selector fabricates variance on every figure it touches, including the two KPI-strip metrics this review had called genuinely computed (R22). The audit is complete; the actual rewiring and fixes have not started. | Q27: TODO.md O7
A28: 3.1d | B28: P3 · Data & Prototype | C28: Activity | D28: Replace real brands with fictional ones | E28: Added | F28: Remove trademark exposure from the demo. | G28: Could a client recognise a real brand on screen? | I28: Not started | J28: 1 | K28: =WORKDAY(L13,1) | L28: =IF(OR(K28="",J28=""),"",WORKDAY(K28,J28-1)) | M28: Tentative — our estimate | N28: Q8 | O28: No real brand names in data, screens or simulator. | P28: Seven real brands in the database, plus Pepsi, Mountain Dew and Lay's in the pricing simulator. Needs a dataset regenerate and reload. | Q28: TODO.md O9
A29: 3.2 | B29: P3 · Data & Prototype | C29: Activity | D29: Rework Portfolio Health Map | E29: Team tracker (reworded: tab exists) | F29: Build lifecycle, growth, revenue, margin and strategic-fit views. | G29: Can the VP identify healthy and underperforming products quickly? | H29: UI/BI Lead | I29: Rework needed | K29: =WORKDAY(L23,1) | L29: =IF(OR(K29="",J29=""),"",WORKDAY(K29,J29-1)) | M29: Tentative — needs an estimate | N29: G2 | O29: Functional Tab 1 | P29: Tab exists. 21 gaps identified in the team's functional review. | Q29: Gap Analysis tab
A30: 3.3 | B30: P3 · Data & Prototype | C30: Activity | D30: Rework Launch Readiness Dashboard | E30: Team tracker (reworded: tab exists) | F30: Build market, supply, channel and pricing readiness views. | G30: Can the user identify launch risks and readiness status? | H30: UI/BI Lead | I30: Rework needed | K30: =WORKDAY(L23,1) | L30: =IF(OR(K30="",J30=""),"",WORKDAY(K30,J30-1)) | M30: Tentative — needs an estimate | N30: G2 | O30: Functional Tab 2 | P30: Tab exists. 15 gaps identified. The Product Manager is served the VP's view, but the persona matrix makes PM primary here. | Q30: Gap Analysis tab
A31: 3.4 | B31: P3 · Data & Prototype | C31: Activity | D31: Rework Profitability Tree | E31: Team tracker (reworded: tab exists) | F31: Build revenue, margin, cost-to-serve and leakage analysis. | G31: Can the user explain why profitability is changing? | H31: Analytics/UI Lead | I31: Rework needed | K31: =WORKDAY(L23,1) | L31: =IF(OR(K31="",J31=""),"",WORKDAY(K31,J31-1)) | M31: Tentative — needs an estimate | N31: G2 | O31: Functional Tab 3 | P31: Tab exists. No gap analysis yet — next for the team. | Q31: —
A32: 3.5 | B32: P3 · Data & Prototype | C32: Activity | D32: Rework SKU Rationalization Simulator | E32: Team tracker (reworded: tab exists) | F32: Build retain/grow/bundle/reposition/sunset recommendations and scenario impact. | G32: Can the user simulate portfolio changes and see revenue/margin/complexity impact? | H32: Analytics/UI Lead | I32: Rework needed | K32: =WORKDAY(L23,1) | L32: =IF(OR(K32="",J32=""),"",WORKDAY(K32,J32-1)) | M32: Tentative — needs an estimate | N32: G2, Q13 | O32: Functional Tab 4 | P32: Tab exists. No gap analysis yet. Outcome labels differ from the team's (Q13). | Q32: —
A33: 3.6 | B33: P3 · Data & Prototype | C33: Activity | D33: Rework Market & VoC Signal Board | E33: Team tracker (reworded: tab exists) | F33: Build customer sentiment, competitor, demand and channel signal views. | G33: Can external signals influence portfolio decisions? | H33: UI/BI Lead | I33: Rework needed | K33: =WORKDAY(L23,1) | L33: =IF(OR(K33="",J33=""),"",WORKDAY(K33,J33-1)) | M33: Tentative — needs an estimate | N33: G2, Q11 | O33: Functional Tab 5 | P33: Tab exists. No gap analysis yet. Competitor content is authored, not fed (Q11). | Q33: —
A34: 3.7 | B34: P3 · Data & Prototype | C34: Activity | D34: Consolidate 12 tabs into 5 | E34: Original 16-phase plan (Frontend 'Done' → rework) | F34: Fold Home, Top-Down Drill, Assortment, Orchestrator and Task Tracker into the five domain tabs. | G34: Can each persona do their job in five tabs? | I34: Not started | J34: 10 | K34: =WORKDAY(L22,1) | L34: =IF(OR(K34="",J34=""),"",WORKDAY(K34,J34-1)) | M34: Tentative — our estimate | N34: 2.8, Q7 | O34: Five domain tabs live; duplicated VP / standard views unified; smoke test covers every tab. | P34: 12 tabs today. The decision journey shows the drill-down belongs inside each tab. | Q34: TODO.md O8
A35: 3.8 | B35: P3 · Data & Prototype | C35: Activity | D35: Backend — FastAPI read API and metric registry | E35: Original 16-phase plan | F35: Serve every displayed figure from PostgreSQL through one metric registry. | G35: Does every figure on screen have one definition and one source? | I35: Not started | J35: 30 | K35: =WORKDAY(MAX(L17,L21),1) | L35: =IF(OR(K35="",J35=""),"",WORKDAY(K35,J35-1)) | M35: Tentative — original plan (6 weeks) | N35: 2.3, 2.7, 3.1a | O35: Read API serves every displayed figure from the registry. | P35: Critical path. Nothing built yet. If Q1 = demo asset, read-only endpoints are enough. | Q35: requirements.txt
A36: 3.9 | B36: P3 · Data & Prototype | C36: Activity | D36: Integration — the app reads from the API | E36: Original 16-phase plan | F36: Replace constant imports with one data hook calling the API. | G36: Is any figure still hardcoded? | I36: Not started | J36: 5 | K36: =WORKDAY(MAX(L35,L34),1) | L36: =IF(OR(K36="",J36=""),"",WORKDAY(K36,J36-1)) | M36: Tentative — original plan (1 week) | N36: 3.7, 3.8 | O36: No figure imported from a constant file. | P36: Nothing in the app calls a server today. | Q36: —
A37: G3 | B37: P3 · Data & Prototype | C37: Gate | D37: Gate 3 — Functional prototype | E37: Team tracker | F37: Five tabs working without AI dependency | G37: — | I37: Not started | L37: =MAX(L26,L27,L28,L29,L30,L31,L32,L33,L34,L36) | M37: Tentative | N37: 3.1b–3.9 | O37: Five tabs working without AI dependency | P37: Excludes 3.2–3.6 until they have estimates, so this date is optimistic (R21). | Q37: —
A38: 4.1 | B38: P4 · AI, Testing & Final Demo | C38: Activity | D38: Design agent responsibilities | E38: Team tracker | F38: Refine Portfolio, Market Signal, Launch, Profitability and Sunset agent roles. | G38: What does each agent monitor, analyze, recommend and hand off? | H38: AI Lead | I38: Not started | J38: 2 | K38: =WORKDAY(L23,1) | L38: =IF(OR(K38="",J38=""),"",WORKDAY(K38,J38-1)) | M38: Tentative — our estimate | N38: G2, Q15 | O38: Agent responsibility matrix | P38: Five agents named in the brief; today's widget is keyword matching. | Q38: —
A39: 4.2 | B39: P4 · AI, Testing & Final Demo | C39: Activity | D39: Implement agentic recommendations | E39: Team tracker | F39: Connect agents to business rules/data and generate explainable recommendations. | G39: Do recommendations lead to an actionable decision? | H39: AI/Tech Lead | I39: Not started | J39: 5 | K39: =WORKDAY(MAX(L35,L38),1) | L39: =IF(OR(K39="",J39=""),"",WORKDAY(K39,J39-1)) | M39: Tentative — original plan (1 week) | N39: 3.8, 4.1, Q10 | O39: Agent-enabled prototype | P39: No model is called today. | Q39: —
A40: 4.3 | B40: P4 · AI, Testing & Final Demo | C40: Activity | D40: End-to-end scenario testing | E40: Team tracker | F40: Test a complete portfolio/launch/rationalization scenario from signal to decision. | G40: Can a VP move from insight to action in one flow? | H40: QA + Product | I40: Not started | J40: 3 | K40: =WORKDAY(MAX(L37,L39),1) | L40: =IF(OR(K40="",J40=""),"",WORKDAY(K40,J40-1)) | M40: Tentative — original plan (testing, 1 week) | N40: G3, 4.2 | O40: Validated end-to-end scenario | P40: Foundations: 16 data checks and a browser smoke test (27/27). Tabs 9–11 are not smoke tested. | Q40: scripts/smoke.mjs
A41: 4.4 | B41: P4 · AI, Testing & Final Demo | C41: Activity | D41: UX and KPI validation | E41: Team tracker | F41: Check usability, KPI correctness, assumptions and consistency across tabs. | G41: Are the outputs understandable and defensible? | H41: QA Lead | I41: Not started | J41: 2 | K41: =WORKDAY(L40,1) | L41: =IF(OR(K41="",J41=""),"",WORKDAY(K41,J41-1)) | M41: Tentative — original plan (testing, 1 week) | N41: 4.3 | O41: QA checklist + fixes | P41: — | Q41: —
A42: 4.5 | B42: P4 · AI, Testing & Final Demo | C42: Activity | D42: Final demo storyline | E42: Team tracker | F42: Create a 10–15 minute VP-focused journey from problem to recommendation and outcome. | G42: Does every tab earn its place and support a decision? | H42: Team Lead | I42: Not started | J42: 2 | K42: =WORKDAY(L41,1) | L42: =IF(OR(K42="",J42=""),"",WORKDAY(K42,J42-1)) | M42: Tentative — our estimate | N42: 4.4, Q9 | O42: Final demo script + slides | P42: Use the end-to-end decision journey as the script. | Q42: Personas & Journey tab
A43: 4.6 | B43: P4 · AI, Testing & Final Demo | C43: Activity | D43: Final review and handover | E43: Team tracker | F43: Close open issues, document assumptions and prepare final submission. | G43: What remains unresolved? Are all scope/KPI/agent requirements covered? | H43: Team Lead | I43: Not started | J43: 2 | K43: =IF(COUNT(L42,L44)=0,"",WORKDAY(MAX(L42,L44),1)) | L43: =IF(OR(K43="",J43=""),"",WORKDAY(K43,J43-1)) | M43: Tentative — our estimate | N43: 4.5, 4.7 | O43: Final prototype + documentation | P43: — | Q43: —
A44: 4.7 | B44: P4 · AI, Testing & Final Demo | C44: Activity | D44: Deployment | E44: Original 16-phase plan | F44: Host the frontend, API and database for the demo. | G44: Is the demo URL stable and the data current? | I44: Not started | K44: =WORKDAY(L41,1) | L44: =IF(OR(K44="",J44=""),"",WORKDAY(K44,J44-1)) | M44: Tentative — needs a duration (original: TBD) | N44: 4.4, Q10 | O44: Frontend, API and database hosted; demo URL stable. | P44: Frontend on Vercel as a static site. Enter a duration in column J to schedule it. | Q44: Links tab
A45: G4 | B45: P4 · AI, Testing & Final Demo | C45: Gate | D45: Gate 4 — Final demo | E45: Team tracker | F45: Agents + simulation + testing + VP decision journey | G45: — | I45: Not started | L45: =IF(L43="","",WORKDAY(L43,1)) | M45: Tentative | N45: 4.1–4.7, Q9 | O45: Agents + simulation + testing + VP decision journey | P45: No deadline set (confirmed 22 Sep). This is the earliest date at the durations above. | Q45: —
A46: 4.8 | B46: P4 · AI, Testing & Final Demo | C46: Activity | D46: Enhancement / production roadmap | E46: Original 16-phase plan | F46: Plan what comes after the demo. | G46: What does the agreed positioning need next? | I46: Not started | K46: =IF(L45="","",WORKDAY(L45,1)) | L46: =IF(OR(K46="",J46=""),"",WORKDAY(K46,J46-1)) | M46: Tentative (original: TBD) | N46: G4, Q1 | O46: Roadmap agreed for the chosen positioning. | P46: Depends on Q1 — a demo asset and a product have very different roadmaps. | Q46: —

Sheet Daily Task Log
A1: Daily Task Log
A2: Retrospective — every entry below is completed work, logged after the fact. No formal daily plan existed before this sheet, so Planned EOD equals Actual EOD throughout; going forward, set Planned EOD before the day starts.
A4: Date | B4: Team Member | C4: Workstream / Module | D4: Task / Activity | E4: What Needs to Be Done | F4: Status | G4: Priority | H4: Dependency / Blocker | I4: Planned EOD | J4: Actual EOD | K4: Remarks
A5: 18 May 2026 | B5: Jaiadithya A / acies-Jai | C5: Frontend Build | D5: Repository and application scaffold | E5: Stand up the React/Vite/Tailwind shell, 3-persona welcome gate, initial tab routing | F5: Done | G5: High | H5: None | I5: — | J5: 20 May 2026 | K5: Inherited — first commits of the project
A6: 21 May – 27 Jul 2026 | B6: Amita, SreeVyshnavi, acies-Jai | C6: Frontend Build | D6: Build all 12 tabs, KPI cards, simulators, agent widget | E6: Deliver the full dashboard surface: Portfolio Health, Launch Readiness, Profitability, SKU Rationalization, Signals, plus supporting modals | F6: Done | G6: High | H6: None | I6: — | J6: 27 Jul 2026 | K6: 369 commits, 4 contributors — compressed to one row; see Timeline tab for detail. Repository then idle 27 Jul – 1 Sep.
A7: 1 Sep 2026 | B7: Guna | C7: Codebase Remediation | D7: Restore type safety, split bundle, extract shared primitives | E7: Re-enable TypeScript checking (bypassed by the previous team); break up the monolithic bundle | F7: Done | G7: High | H7: None | I7: 1 Sep 2026 | J7: 1 Sep 2026 | K7: First commit of the remediation phase
A8: 1 Sep 2026 | B8: Guna | C8: Codebase Remediation | D8: Repair 1,237 invalid Tailwind colour classes | E8: Fix broken utility classes across 63 files so styling actually applies | F8: Done | G8: Medium | H8: None | I8: 1 Sep 2026 | J8: 1 Sep 2026
A9: 1 Sep 2026 | B9: Guna | C9: Codebase Remediation | D9: Route all 43 overlays through shared modal primitives | E9: Deduplicate modal/overlay implementations onto one shared component set | F9: Done | G9: Medium | H9: None | I9: 1 Sep 2026 | J9: 1 Sep 2026
A10: 9 Sep 2026 | B10: Guna | C10: Dataset Generation | D10: Search for a usable real dataset | E10: Determine whether real transaction-level data exists to ground the app's metrics | F10: Done | G10: High | H10: None | I10: 9 Sep 2026 | J10: 9 Sep 2026 | K10: None found — only aggregate notebook outputs. Decided to generate a synthetic dataset instead (Decision D1).
A11: 14 Sep 2026 | B11: Guna | C11: Dataset Generation | D11: Build and validate the synthetic FMCG dataset | E11: Generate 119 SKUs x 7 countries x 4 channels x 2 years, seeded, reconciling to the source figures | F11: Done | G11: High | H11: Dataset search (row above) | I11: 14 Sep 2026 | J11: 14 Sep 2026 | K11: 368,013 fact rows; 16 of 16 validation targets met
A12: 14 Sep 2026 | B12: Guna | C12: Documentation | D12: Write data model specification and generation plan | E12: Document the 13-table schema (types, keys, grain) and the generation rules before building the database | F12: Done | G12: High | H12: None | I12: 14 Sep 2026 | J12: 14 Sep 2026
A13: 17 Sep 2026 | B13: Guna | C13: Product Research | D13: Publish Report 1 — Metric Dictionary | E13: Define every displayed metric and justify why it's calculated | F13: Done | G13: High | H13: None | I13: 17 Sep 2026 | J13: 17 Sep 2026 | K13: Found only 2 of 6 required KPIs properly computed
A14: 17 Sep 2026 | B14: Guna | C14: Product Research | D14: Publish Report 2 — Twelve Tabs to Five | E14: Audit all 12 tabs per persona and recommend which to keep | F14: Done | G14: High | H14: None | I14: 17 Sep 2026 | J14: 17 Sep 2026
A15: 17 Sep 2026 | B15: Guna | C15: Product Research | D15: Publish Report 3 — Worth Building? | E15: Assess the competitive landscape and whether this is worth building | F15: Done | G15: Medium | H15: None | I15: 17 Sep 2026 | J15: 17 Sep 2026
A16: 20 Sep 2026 | B16: Guna | C16: Codebase Remediation | D16: Repo cleanup, phases A–C | E16: Remove scratch files and dead code; split 9 oversized files into 30 modules | F16: Done | G16: High | H16: None | I16: 20 Sep 2026 | J16: 20 Sep 2026 | K16: 187 files removed; 22,619 -> 11,854 lines (-47%)
A17: 20 Sep 2026 | B17: Guna | C17: Codebase Remediation | D17: Delete dead Express server and unused dependencies | E17: Confirm the backend language (Python/FastAPI) and remove the Node backend remnants | F17: Done | G17: Medium | H17: Backend language decision | I17: 20 Sep 2026 | J17: 20 Sep 2026 | K17: 124 npm packages removed
A18: 20 Sep 2026 | B18: Guna | C18: Database Setup | D18: Create PostgreSQL role and database; build the 13-table schema | E18: Stand up ppl_intelligence with a least-privilege application role | F18: Done | G18: High | H18: Postgres superuser password | I18: 20 Sep 2026 | J18: 20 Sep 2026 | K18: Fixed two real psql scripting bugs along the way
A19: 20 Sep 2026 | B19: Guna | C19: Database Setup | D19: Load the generated dataset into PostgreSQL | E19: COPY all 13 tables in FK order and reconcile against the generator's targets | F19: Done | G19: High | H19: Schema built (row above) | I19: 20 Sep 2026 | J19: 20 Sep 2026 | K19: 377,364 rows loaded in 44.9s; reconciles to $473.0M / +8.29% / 38.55%
A20: 20 Sep 2026 | B20: Guna | C20: Architecture & Planning | D20: Draw Now / Next / Future system architecture | E20: Document the current state, the trustworthy-demo target, and the long-term agentic target | F20: Done | G20: Medium | H20: None | I20: 20 Sep 2026 | J20: 20 Sep 2026 | K20: Excalidraw-ready Mermaid diagrams
A21: 21 Sep 2026 | B21: Guna | C21: Stakeholder Prep | D21: Draft stakeholder pitch and 12 open questions | E21: Turn the three reports into a decision-ready document with a recommendation and a default per question | F21: Done | G21: High | H21: Reports 1-3 | I21: 21 Sep 2026 | J21: 21 Sep 2026
A22: 22 Sep 2026 | B22: Guna | C22: Project Tracking | D22: Build the merged project tracker | E22: Combine the team's P1-P4 plan, gap analyses and persona matrix with our data and architecture work into one tracker | F22: Done | G22: High | H22: Team tracker reviewed | I22: 22 Sep 2026 | J22: 22 Sep 2026 | K22: Replaced 5 competing plans in circulation
A23: 23 Sep 2026 | B23: Guna | C23: Persona / UI Audit | D23: Publish the 'Nine Tabs, Zero Backend' tab audit | E23: Check what's built, real vs. fabricated data, and backend status for every tab and persona | F23: Done | G23: High | H23: None | I23: 23 Sep 2026 | J23: 23 Sep 2026
A24: 23 Sep 2026 | B24: Guna | C24: Persona / UI Audit | D24: Prototype persona-specific sidebar ordering | E24: Reorder the 9 sidebar tabs per role using the persona matrix; revert the earlier landing-page change | F24: Done | G24: Medium | H24: Tab audit (row above) | I24: 23 Sep 2026 | J24: 23 Sep 2026 | K24: Found and logged a real bug: role does not update on hashchange (TODO.md O10)
A25: 23 Sep 2026 | B25: Guna | C25: Metric Integrity Audit | D25: Catalogue every formula in the application | E25: Verify each displayed metric against source: real, real-formula-fake-input, or fabricated | F25: Done | G25: High | H25: None | I25: 23 Sep 2026 | J25: 23 Sep 2026 | K25: Found the timeline selector fabricates variance on every figure, including the 2 metrics previously found genuinely computed
A26: 24 Sep 2026 | B26: Guna | C26: Project Tracking | D26: Update tracker with completed-task status | E26: Reflect progress on personas (1.3) and metric integrity (3.1c); log the timeline-noise finding as a new risk (R22) | F26: Done | G26: Medium | H26: Formula audit (row above) | I26: 24 Sep 2026 | J26: 24 Sep 2026 | K26: Fixed a column-shift bug from this same edit
A27: 25 Sep 2026 | B27: Guna | C27: Project Tracking | D27: Add this daily task log | E27: Add a per-day task log in the team's own tracking format | F27: Done | G27: Low | H27: None | I27: 25 Sep 2026 | J27: 25 Sep 2026 | K27: This sheet
A28: 29 Sep 2026 | B28: Guna | C28: Database Integration | D28: O1 threshold audit — dollar-cutoff calibration | E28: Decide and implement how hand-tuned dollar thresholds (Netherlands / France-Austria-Poland catalog cutoffs, Introduction-stage lifecycle cutoff) should be rescaled now that real per-SKU revenue is live — verify selectivity is preserved, not just unit-converted | F28: Done | G28: High | H28: Live SKU revenue (skuRevenueM) | I28: 29 Sep 2026 | J28: 29 Sep 2026 | K28: Mean-ratio rescale was wrong for SKUHoldingsMatrix — real revenue is Pareto-skewed vs. the old uniform hand-typed values; caught by checking selectivity numerically, fixed with rank-preserving constants instead
A29: 30 Sep 2026 | B29: Guna | C29: Branding / UI | D29: Extract and wire the product logo | E29: Crop the cube mark from the reference Logo.png, produce header / login / favicon assets, replace placeholder icons in Header, LoginPage and WelcomeGate | F29: Done | G29: Medium | H29: Logo.png reference image | I29: 30 Sep 2026 | J29: 30 Sep 2026 | K29: Also replaced WelcomeGate’s generic "AI network lines" background with a product-lifecycle-curve motif matching the brand
A30: 30 Sep 2026 | B30: Guna | C30: UI / Navigation | D30: Convert "Switch profile" into an inline dropdown | E30: Replace the full-screen navigate-back-to-Welcome-Gate flow with an in-header role picker so switching persona no longer leaves the current tab | F30: Done | G30: Medium | H30: None | I30: 30 Sep 2026 | J30: 30 Sep 2026 | K30: Removed the now-dead handleSwitchPersona / onSwitchPersona plumbing it replaced
A31: 30 Sep 2026 | B31: Guna | C31: Product Research | D31: Review daily team call; audit Top-Down Drilldown against the database | E31: Check whether the OTIF / fulfillment drill-down (LATAM / EMEA / APAC) the team reviewed live on the call is backed by real data | F31: Done | G31: High | H31: Database connected (29 Sep) | I31: 30 Sep 2026 | J31: 30 Sep 2026 | K31: Found the regions, managers and OTIF numbers shown are entirely fictional — the DB only has 7 European countries; real lead-time / stockout signals exist but are not wired to this screen
A32: 30 Sep 2026 | B32: Guna | C32: Product Research | D32: Decide real vs. illustrative regions for the drill-down | E32: Choose whether Top-Down Drilldown should be relabeled to the DB’s real 7 countries / 3 European regions, or stay APAC / EMEA / LATAM as demo framing | F32: Not started | G32: High | H32: Team decision | I32: — | J32: — | K32: Blocks defining a real OTIF metric; raised in the 30 Sep call
A33: 30 Sep 2026 | B33: Guna | C33: Metrics / Backend | D33: Define and compute a real OTIF metric | E33: fact_sales only has stock_out_flag and lead_time_days, not literal ordered-vs-received quantities — pick a derivable definition and add it as a SQL function, same pattern as the other live metrics | F33: Not started | G33: High | H33: Region decision (row above) | I33: — | J33: — | K33: Raised in the 30 Sep call as the model for detect → diagnose → simulate → recommend elsewhere in the app
A34: 30 Sep 2026 | B34: Guna | C34: Frontend / Search | D34: Bulk multi-SKU search and combined report | E34: Let a user select several SKUs at once (not just one at a time) and generate a single combined report | F34: Not started | G34: Medium | H34: None | I34: — | J34: — | K34: Confirmed missing app-wide; raised in the 30 Sep call
A35: 30 Sep 2026 | B35: Guna | C35: Frontend | D35: Report download / export | E35: Confirm and, if missing, add a way to download what is on screen — currently only scattered per-tab CSV buttons exist (SKU Performance, Rationalization) | F35: Not started | G35: Medium | H35: None | I35: — | J35: — | K35: Left as an open question in the 30 Sep call
A36: 30 Sep 2026 | B36: Guna | C36: Codebase Remediation | D36: O1 threshold audit — percent constants | E36: Wire the hand-tuned % constants (cannibalization uplift, waste write-off, complexity savings, etc.) to live revenue inputs; the constants themselves stay as-is per the 29 Sep decision | F36: Not started | G36: Medium | H36: Live skuRevenueM in the affected files | I36: — | J36: — | K36: Decided 29 Sep: treat as demo-plausible assumptions, no recalibration needed — just needs wiring

Sheet Open Questions
A1: Open Questions — decisions we need
A2: Each has a recommendation, so 'agreed' is a complete answer. 'Needed by' follows the meeting date. Light yellow = please fill in.
A4: # | B4: Question | C4: Why it matters | D4: Options | E4: Recommendation | F4: Default if unanswered | G4: Who answers | H4: Meeting | I4: Needed by | J4: Status | K4: Answer / decision
A5: Q1 | B5: Is Lab 8 a capability showcase or a product that competes? | C5: Decides investment in ingestion, security and competitor data. | D5: A · GTM demo asset B · Internal accelerator C · Product | E5: A, keeping B open | F5: Build as a GTM demo asset | G5: Programme owner | H5: M1 | I5: =IFERROR(IF(INDEX('Stakeholder Meetings'!$G$5:$G$12,MATCH(LEFT(H5,2),'Stakeholder Meetings'!$A$5:$A$12,0))="","",INDEX('Stakeholder Meetings'!$G$5:$G$12,MATCH(LEFT(H5,2),'Stakeholder Meetings'!$A$5:$A$12,0))),"") | J5: Open
A6: Q2 | B6: Which revenue baseline is canonical — $473M or $851M? | C6: Every downstream figure and the metric registry depend on it. | D6: $473M (validated dataset) $851M (in more places — 18 source lines) | E6: $473M | F6: $473M | G6: Programme owner; finance SME | H6: M2 | I6: =IFERROR(IF(INDEX('Stakeholder Meetings'!$G$5:$G$12,MATCH(LEFT(H6,2),'Stakeholder Meetings'!$A$5:$A$12,0))="","",INDEX('Stakeholder Meetings'!$G$5:$G$12,MATCH(LEFT(H6,2),'Stakeholder Meetings'!$A$5:$A$12,0))),"") | J6: Open
A7: Q3 | B7: Two required KPIs — time-to-market and launch success — have no data. 0 of 119 SKUs have a launch date. | C7: 2 of the 6 required KPIs cannot be computed; the launch closed loop needs the same data. | D7: Synthetic launch table Drop both KPIs Source real launch data | E7: Synthetic launch table (~2 days) | F7: Add a synthetic launch table | G7: Programme owner | H7: M2 | I7: =IFERROR(IF(INDEX('Stakeholder Meetings'!$G$5:$G$12,MATCH(LEFT(H7,2),'Stakeholder Meetings'!$A$5:$A$12,0))="","",INDEX('Stakeholder Meetings'!$G$5:$G$12,MATCH(LEFT(H7,2),'Stakeholder Meetings'!$A$5:$A$12,0))),"") | J7: Open
A8: Q4 | B8: Gross Profit, Net Profit and SG&A cards have no cost basis — no opex columns exist. | C8: An undefendable profit figure is the likeliest thing to end a client demo badly. | D8: Remove the cards Extend the model with opex | E8: Remove | F8: Remove the three cards | G8: Programme owner; finance SME | H8: M2 | I8: =IFERROR(IF(INDEX('Stakeholder Meetings'!$G$5:$G$12,MATCH(LEFT(H8,2),'Stakeholder Meetings'!$A$5:$A$12,0))="","",INDEX('Stakeholder Meetings'!$G$5:$G$12,MATCH(LEFT(H8,2),'Stakeholder Meetings'!$A$5:$A$12,0))),"") | J8: Open
A9: Q5 | B9: 12 of 20 designed metrics have no value. Compute or remove? | C9: KPI strips render empty on four tabs. | D9: Compute those the data supports Delete the rest | E9: Compute what maps; delete the rest | F9: Compute what maps; delete the rest | G9: Programme owner | H9: M2 | I9: =IFERROR(IF(INDEX('Stakeholder Meetings'!$G$5:$G$12,MATCH(LEFT(H9,2),'Stakeholder Meetings'!$A$5:$A$12,0))="","",INDEX('Stakeholder Meetings'!$G$5:$G$12,MATCH(LEFT(H9,2),'Stakeholder Meetings'!$A$5:$A$12,0))),"") | J9: Open
A10: Q6 | B10: Netherlands margin: the source says lowest (38.20%); our data says highest (40.27%). Which is right? | C10: Credibility with an informed viewer; a gap in our validation. | D10: Source is right — fix generator, add a check Source was an artefact | E10: Treat the source as authoritative | F10: Fix the generator; add a validation check | G10: FMCG / finance SME | H10: M2 | I10: =IFERROR(IF(INDEX('Stakeholder Meetings'!$G$5:$G$12,MATCH(LEFT(H10,2),'Stakeholder Meetings'!$A$5:$A$12,0))="","",INDEX('Stakeholder Meetings'!$G$5:$G$12,MATCH(LEFT(H10,2),'Stakeholder Meetings'!$A$5:$A$12,0))),"") | J10: Open
A11: Q7 | B11: Which five tabs? And should the Product Manager see the VP's Launch Readiness view? | C11: Gates UI/UX and the tab consolidation. | D11: The brief's five modules as named in the team tracker (3.2–3.6) | E11: Adopt those five; fold Home, Top-Down Drill, Assortment, Orchestrator and Task Tracker into them. Give the PM its own launch view — the persona matrix makes PM primary there. | F11: None — needs an owner | G11: Programme owner | H11: M3 | I11: =IFERROR(IF(INDEX('Stakeholder Meetings'!$G$5:$G$12,MATCH(LEFT(H11,2),'Stakeholder Meetings'!$A$5:$A$12,0))="","",INDEX('Stakeholder Meetings'!$G$5:$G$12,MATCH(LEFT(H11,2),'Stakeholder Meetings'!$A$5:$A$12,0))),"") | J11: Open
A12: Q8 | B12: Rename the real brands in the demo? | C12: Seven real brands in the SKU list; Pepsi, Mountain Dew and Lay's in the pricing simulator. | D12: Rename all to fictional brands Keep competitor names as labelled references | E12: Rename all | F12: Rename all | G12: Programme owner | H12: M3 | I12: =IFERROR(IF(INDEX('Stakeholder Meetings'!$G$5:$G$12,MATCH(LEFT(H12,2),'Stakeholder Meetings'!$A$5:$A$12,0))="","",INDEX('Stakeholder Meetings'!$G$5:$G$12,MATCH(LEFT(H12,2),'Stakeholder Meetings'!$A$5:$A$12,0))),"") | J12: Open
A13: Q9 | B13: When is the first demo, and to whom? | C13: No deadline is set (confirmed 22 Sep). The team tracker's 20 working days from 3 Sep (to 30 Sep) is a placeholder. | D13: — | E13: Set a date; the Overview shows the earliest at planned durations | F13: None — needs an owner | G13: Programme owner | H13: M1 | I13: =IFERROR(IF(INDEX('Stakeholder Meetings'!$G$5:$G$12,MATCH(LEFT(H13,2),'Stakeholder Meetings'!$A$5:$A$12,0))="","",INDEX('Stakeholder Meetings'!$G$5:$G$12,MATCH(LEFT(H13,2),'Stakeholder Meetings'!$A$5:$A$12,0))),"") | J13: Open
A14: Q10 | B14: Where does it run, what is the LLM budget, and is 'the LLM explains, never computes' agreed? | C14: Backend hosting, agent design and running cost. | D14: — | E14: Agree the principle; re-price models before quoting | F14: None — needs an owner | G14: Programme owner; budget holder | H14: M4 | I14: =IFERROR(IF(INDEX('Stakeholder Meetings'!$G$5:$G$12,MATCH(LEFT(H14,2),'Stakeholder Meetings'!$A$5:$A$12,0))="","",INDEX('Stakeholder Meetings'!$G$5:$G$12,MATCH(LEFT(H14,2),'Stakeholder Meetings'!$A$5:$A$12,0))),"") | J14: Open
A15: Q11 | B15: Does the Signals Board need a real competitor feed? | C15: A second data source with its own grain, refresh and licensing. | D15: Illustrative, clearly labelled Real feed | E15: Illustrative if Q1 = A | F15: Keep illustrative, labelled | G15: Programme owner | H15: M1 | I15: =IFERROR(IF(INDEX('Stakeholder Meetings'!$G$5:$G$12,MATCH(LEFT(H15,2),'Stakeholder Meetings'!$A$5:$A$12,0))="","",INDEX('Stakeholder Meetings'!$G$5:$G$12,MATCH(LEFT(H15,2),'Stakeholder Meetings'!$A$5:$A$12,0))),"") | J15: Open
A16: Q12 | B16: Is the repository public? | C16: A database password is in pushed git history (a3a3c54). It protects nothing today, but the follow-up depends on visibility. | D16: — | E16: Confirm visibility | F16: Treat as private; value already rotated | G16: Guna | H16: M4 | I16: =IFERROR(IF(INDEX('Stakeholder Meetings'!$G$5:$G$12,MATCH(LEFT(H16,2),'Stakeholder Meetings'!$A$5:$A$12,0))="","",INDEX('Stakeholder Meetings'!$G$5:$G$12,MATCH(LEFT(H16,2),'Stakeholder Meetings'!$A$5:$A$12,0))),"") | J16: Open
... A19: Q15 | B19: Which agent decisions may be automated, and which only recommended? | C19: Decides agent design (4.1). From the team's validation tracker (agentic scope). | D19: Recommend only Automate low-risk alerts Automate actions | E19: Agents detect and recommend; a person approves every action | F19: Recommend only | G19: Programme owner | H19: M4 | I19: =IFERROR(IF(INDEX('Stakeholder Meetings'!$G$5:$G$12,MATCH(LEFT(H19,2),'Stakeholder Meetings'!$A$5:$A$12,0))="","",INDEX('Stakeholder Meetings'!$G$5:$G$12,MATCH(LEFT(H19,2),'Stakeholder Meetings'!$A$5:$A$12,0))),"") | J19: Open

Sheet Stakeholder Meetings
A1: Stakeholder Meetings — clearing scope and misunderstandings
A2: Schedule M8 and M1 first. Light yellow = please fill in.
A4: # | B4: Meeting | C4: Purpose | D4: Questions to settle | E4: Suggested attendees | F4: Pre-read | G4: Proposed date | H4: Length | I4: Status | J4: Decisions / outcome
A5: M8 | B5: Team plan alignment | C5: Adopt this merged tracker as the only plan; put names against roles; estimate 3.2–3.6. | D5: D13, R19, R21 | E5: Project team | F5: This tracker | H5: 45 min | I5: Not scheduled
A6: M1 | B6: Scope and positioning | C6: Agree what Lab 8 is for, its deadline, and what the demo leads with. | D6: Q1, Q9, Q11, Q14 | E6: Lab 8 programme owner; Acies GTM or practice lead; Guna | F6: pitch.md; Report 3 | H6: 60 min | I6: Not scheduled
A7: M2 | B7: Metrics, data and decision rules | C7: One revenue baseline, the six KPIs, unsupported cards, and one decision vocabulary. | D7: Q2, Q3, Q4, Q5, Q6, Q13 | E7: Programme owner; FMCG or finance SME; Guna | F7: Report 1; Gap Analysis tab | H7: 60 min | I7: Not scheduled
A8: M3 | B8: Tabs and personas sign-off | C8: Approve the five domain tabs and what each persona sees. | D8: Q7, Q8 | E8: Programme owner; UX / design; persona representatives if available; Guna | F8: Report 2; Personas & Journey tab | H8: 45 min | I8: Not scheduled
A9: M4 | B9: Delivery and infrastructure | C9: Hosting, LLM budget, and what agents may do on their own. | D9: Q10, Q12, Q15 | E9: Programme owner; infrastructure / IT; budget holder; Guna | F9: Architecture Roadmap tab | H9: 45 min | I9: Not scheduled
A10: M5 | B10: Reverse KT with the previous team | C10: Play back our understanding; close gaps on data origin, persona views and the real brand names. | D10: — | E10: Amita; SreeVyshnavi; acies-Jai / Jaiadithya A; Guna | F10: Handover Findings tab | H10: 60 min | I10: Not scheduled
A11: M6 | B11: Weekly status | C11: Walk this tracker; unblock anything Blocked or At risk. | D11: As needed | E11: Programme owner; project team | F11: This tracker | G11: Weekly | H11: 30 min | I11: Not scheduled
A12: M7 | B12: Demo dry run | C12: Rehearse the demo end to end before a client sees it. | D12: — | E12: Programme owner; one VP-level reviewer | F12: Personas & Journey tab (section C) | H12: 60 min | I12: Not scheduled

Sheet Gap Analysis
A1: Gap Analysis — requirements backlog
A2: The team's functional reviews, carried verbatim (Research_doc/…Project_Tracker 1.xlsx). 'Plan step' and 'Our note' are added. Profitability, SKU Rationalization and Signals have no review yet.
A4: # | B4: Module | C4: Area | D4: What the existing solution shows | E4: Gap | F4: Recommended improvement | G4: Decision supported / business impact | H4: Validation needed | I4: Team status | J4: Plan step | K4: Our note
A5: 1 | B5: Portfolio Health | C5: Executive KPI layer | D5: Net Sales $480M; Avg Gross Margin 38.47%; Revenue Concentration 27.81%; Long-tail SKU Burden 66.7%; second KPI row includes Revenue, SKU Count, Growth, Orders Today, Forecast Attainment. | E5: Strong executive KPI coverage, but the KPI hierarchy mixes strategic portfolio metrics with operational metrics. 'Orders – Today' may be useful operationally but should be validated as a VP portfolio-health KPI. | F5: Separate Strategic Portfolio KPIs from Operational Signals. Consider Portfolio Revenue vs Target, Gross Margin vs Target, Revenue at Risk, Portfolio ROI/Contribution, Long-tail Burden, and Growth. Move Orders Today to an operational/signal layer if not decision-critical. | G5: What requires executive attention at portfolio level today? | H5: Validate KPI ownership and executive use cases. | I5: Potential Gap – Validate | J5: 3.2
A6: 2 | B6: Portfolio Health | C6: KPI targets & variance | D6: Several cards show TARGET, but some target fields display '-' while others have explicit targets such as $900M, 100 SKUs, 10%, 5000, 97%. | E6: Target availability is inconsistent. A KPI without a defined target cannot reliably indicate health or trigger action. | F6: Define target, benchmark and tolerance for every strategic KPI. Show Actual / Target / Variance / Trend consistently. | G6: Are we on track against the agreed portfolio objectives? | H6: Confirm target source, period and tolerance by KPI. | I6: Needs Business Validation | J6: 2.3
A7: 3 | B7: Portfolio Health | C7: Portfolio Health Score | D7: 88% HEALTH with 'OPTIMAL / ON-TRACK' and a statement about high-margin cash cows and growing products. | E7: The overall score is decision-friendly but its composition is not visible. Users cannot easily see which dimensions produced 88%. | F7: Add score decomposition: profitability, growth, concentration, lifecycle, complexity, risk, customer/market health and supply/service. Show weights, thresholds and top positive/negative drivers. | G7: Why is portfolio health 88%, and what could change it? | H7: Validate scoring model, weights and thresholds. | I7: Potential Gap – Validate | J7: 3.2
A8: 4 | B8: Portfolio Health | C8: Lifecycle Journey | D8: 119 SKUs reconcile across Introduction 7, Growth 37, Maturity 54, Decline 21. Revenue shown by stage totals $10,592M. | E8: Lifecycle view is useful for portfolio shape and stage efficiency. It primarily describes where products are; it does not explicitly prescribe what to do. | F8: Add stage-specific actions: invest, scale, defend, optimize, reposition, harvest or sunset, with revenue/margin/risk implications. | G8: Where should we invest or intervene across the lifecycle? | H8: Validate lifecycle rules and action playbooks. | I8: Potential Gap – Validate | J8: 3.2
A9: 5 | B9: Portfolio Health | C9: Lifecycle efficiency | D9: Growth is labeled Most Efficient; Decline Least Efficient with ratios 112.5 and 48.0. | E9: The ratio formula and business meaning are not visible. Users may not know whether the ratio represents revenue/SKU, margin/SKU, growth efficiency or another measure. | F9: Expose ratio definition, formula, benchmark and interpretation. Allow drill-down to products causing stage inefficiency. | G9: Which lifecycle stage creates or destroys the most value? | H9: Confirm formula and benchmark logic. | I9: Needs Logic Validation | J9: 2.3
A10: 6 | B10: Portfolio Health | C10: Portfolio data reconciliation | D10: Top cards show Net Sales $480M and Portfolio Revenue $1,071.1M; lifecycle section shows Total Revenue $10,592M. Product examples show revenues such as $137.38M. | E10: These figures may represent different scopes, periods, currencies or aggregation levels, but the screenshot does not make the distinctions clear. | F10: Add period, currency, scope and data-source labels. Reconcile portfolio totals with lifecycle, matrices and SKU-level views or clearly explain why they differ. | G10: Can executives trust that all portfolio views use consistent data? | H10: Perform data reconciliation across all displayed revenue metrics. | I10: Critical Validation | J10: 3.1c | K10: Confirmed 22 Sep: the lifecycle 'Total Revenue' sums a per-SKU field that is not in $M (LifecycleHealthPanel.tsx:100) — about 22× actual net sales. See R18.
A11: 7 | B11: Portfolio Health | C11: Portfolio SKU Count | D11: 119 SKUs; target 100; trend says -3 SKUs rationalized. | E11: Good context for complexity, but SKU count alone does not indicate whether rationalization created value. | F11: Pair SKU count with gross margin contribution, revenue retained/lost, complexity cost removed, working capital released and service/customer impact. | G11: Did SKU rationalization actually improve the portfolio? | H11: Validate rationalization outcome metrics. | I11: Potential Gap – Validate | J11: 3.2 | K11: The dataset has 119 SKUs; the target of 100 is authored, not derived.
A12: 8 | B12: Portfolio Health | C12: Long-tail SKU Burden | D12: 66.7% and note '68 SKUs <1% REV'. Long-tail view also uses bottom 70% and says 18 long-tail items consume massive supplier overhead. | E12: The screen identifies a long-tail problem, which is valuable. However, revenue-only screening can miss strategically important low-volume products and operational complexity drivers. | F12: Add margin, cost-to-serve, supplier count, component/commonality, changeovers, inventory, customer/channel dependency and strategic role before recommending pruning. | G12: Which SKUs are truly value-dilutive versus strategically necessary? | H12: Validate long-tail definition and strategic-exception rules. | I12: Potential Gap – Validate | J12: 2.3 | K12: Report 1 also found this metric structurally inflated: the mean SKU share (0.84%) is below the 1% threshold, so an average SKU counts as long tail.
A13: 9 | B13: Portfolio Health | C13: Investment vs Return Margin Map | D13: Products are segmented into Quick Wins, Strategic, Niche and Avoid/High Risk; investment is on x-axis and return margin on y-axis; approval action is available. | E13: This supports capital allocation, but 'return' and decision thresholds need clearer definitions. A margin percentage alone may not capture absolute value, payback or risk. | F13: Use incremental ROI/NPV/payback or contribution where appropriate; show investment, incremental revenue, margin contribution, risk, time-to-value and scenario outcome. | G13: Where should incremental investment go? | H13: Validate return definition and investment decision methodology. | I13: Potential Gap – Validate | J13: 3.2
A14: 10 | B14: Portfolio Health | C14: Investment approval workflow | D14: Cards include Review Metrics and Approve Investment; portfolio also has an Executive Approval Board with meeting/reminder actions. | E14: Approval is present, but the decision record and governance trail are not evident from the screenshots. | F14: Add recommendation, rationale, financial case, risk, owner, approver, decision date, conditions, approval/rejection, and audit history. | G14: Can an executive make and track a defensible investment decision? | H14: Validate approval governance and audit requirements. | I14: Potential Gap – Validate | J14: 3.2
A15: 11 | B15: Portfolio Health | C15: Revenue vs Performance Matrix | D15: Portfolio is segmented into High Performers, Underperformers, Hidden Growth and Attention Required; product cards have Authorize Strategy. | E15: Useful segmentation, but the underlying Performance Score is not explained. The labels may hide multiple metrics. | F15: Show performance score decomposition: growth, margin, forecast attainment, service, customer/market signals, etc. Define quadrant thresholds and recommended actions. | G15: Which products deserve investment, intervention or repositioning? | H15: Validate score formula and quadrant rules. | I15: Potential Gap – Validate | J15: 3.2
A16: 12 | B16: Portfolio Health | C16: Portfolio Alerts | D16: Four brand alerts show percentages (92%, 85%, 87%, 89%); header says 2 Critical. | E16: Alerts are actionable via Review, but the meaning of the percentage and why two are critical is unclear from the screen. | F16: Use explicit alert semantics: severity, trigger, metric, threshold, trend, business impact, owner and recommended action. Ensure critical count reconciles with alert list. | G16: What needs immediate intervention and why? | H16: Validate alert scoring, severity and count logic. | I16: Needs Logic Validation | J16: 3.2
A17: 13 | B17: Portfolio Health | C17: Executive Approval Board | D17: Three pending items include SKU rationalization, compliance certification and launch readiness criteria, with wait times. | E17: This is useful as an action queue, but items span different decision types and lack visible business impact/context. | F17: Prioritize by value at risk, decision deadline, financial impact, customer impact and risk. Add recommended decision and dependencies. | G17: Which pending decision should the executive address first? | H17: Validate prioritization criteria and workflow states. | I17: Potential Gap – Validate | J17: 3.2
A18: 14 | B18: Portfolio Health | C18: Pareto SKU Concentration | D18: Top 10%, Top 30%, Bottom 70% views; top 10% 26.4% sales and top 30% 60.4%; long-tail insights. | E18: Strong concentration analysis, but revenue concentration alone does not identify optimal portfolio actions. | F18: Extend Pareto with gross margin, contribution, complexity cost, inventory, supplier/component dependency and strategic/customer role. Link candidates directly to rationalization simulation. | G18: Where is concentration creating risk or opportunity? | H18: Validate additional dimensions and action linkage. | I18: Potential Gap – Validate | J18: 3.2
A19: 15 | B19: Portfolio Health | C19: Rationalization linkage | D19: Approval item proposes Phase 1 sunset of 15 low-margin tail products. | E19: The dashboard surfaces rationalization decisions, but the visible Pareto/long-tail views do not show a quantified before/after business case for the 15 SKUs. | F19: Connect candidate selection to a rationalization simulator: revenue at risk, margin gain, inventory release, supplier/complexity savings, customer impact and replacement options. | G19: Which SKU set should be removed to maximize value with minimum downside? | H19: Validate rationalization model and exception handling. | I19: Strategic Enhancement | J19: 3.5
A20: 16 | B20: Portfolio Health | C20: Strategic exceptions | D20: Low-volume/long-tail products may still have strategic roles, but no explicit exception mechanism is visible. | E20: Revenue-based pruning can incorrectly target products that support key customers, channels, geographies, bundles or future platforms. | F20: Add strategic-role flags and exceptions: anchor customer, channel requirement, regulatory need, bundle dependency, innovation role, platform dependency. | G20: Which low-performing SKUs must be retained and why? | H20: Confirm strategic exception taxonomy. | I20: Potential Gap – Validate | J20: 2.5
A21: 17 | B21: Portfolio Health | C21: Scenario / What-if portfolio planning | D21: Investment map has capital allocation actions and rationalization is referenced, but an integrated portfolio scenario comparison is not visible. | E21: Portfolio health is largely descriptive. A stronger decision cockpit would allow leaders to test actions before approving them. | F21: Enable scenarios such as invest, price change, discontinue, launch, reposition, bundle, or increase/decrease distribution, with revenue, margin, SKU count, complexity and risk impact. | G21: What happens to the portfolio if we take this action? | H21: Validate required scenario levers and business rules. | I21: Strategic Enhancement | J21: 3.2
A22: 18 | B22: Portfolio Health | C22: Cross-functional root cause | D22: Portfolio Health contains financial, lifecycle and operational-style indicators. | E22: The screen can identify where performance is weak, but root causes may sit in supply, pricing, customer, quality, market or product complexity. | F22: Link portfolio exceptions to Profitability, Signals, Launch Readiness and SKU Assortment so the user can move from symptom to cause to action. | G22: Why is the portfolio/product underperforming? | H22: Validate cross-tab navigation and ownership. | I22: Strategic Enhancement | J22: 3.7
A23: 19 | B23: Portfolio Health | C23: Action-to-impact tracking | D23: Review, Approve Investment, Authorize Strategy, Schedule Meeting and Remind Later actions are visible. | E23: Actions are present, but closed-loop measurement of approved decisions is not visible. | F23: Track approved action → owner → due date → expected impact → actual impact → variance → corrective action. | G23: Did the decision deliver the expected value? | H23: Validate action tracking and benefit-realization process. | I23: Potential Gap – Validate | J23: 2.1
A24: 20 | B24: Portfolio Health | C24: External/customer context | D24: The current screens are primarily internal performance and portfolio analytics. | E24: Portfolio decisions can be incomplete if customer needs, competitive moves and market signals are not incorporated. | F24: Connect market/VoC signals, competitor changes and customer demand signals to affected products and portfolio decisions. | G24: Should we invest, reposition or retire based on market/customer evidence? | H24: Validate external-data availability and signal governance. | I24: Strategic Enhancement | J24: 3.6
... A35: 31 | B35: Launch Readiness | C35: Milestone Tracking | D35: Milestones show statuses such as Completed/In Progress and completion percentage. Current: Progress is visually tracked. | E35: A 50% or 85% completion value does not itself indicate launch risk. | F35: Add planned date, expected/actual date, dependency, owner, delay and impact on Go-Live. | G35: Converts progress tracking into launch-risk management. | H35: Validate milestone dates, ownership and dependency data. | I35: Open | J35: 3.3
A36: 32 | B36: Launch Readiness | C36: Launch Decision | D36: Overall Launch Readiness is represented as a percentage. Current: The user receives a readiness score such as 79%. | E36: A percentage alone does not directly answer whether the SKU should launch. | F36: Introduce GO / CONDITIONAL GO / NO-GO with conditions that must be resolved. | G36: Creates a clear executive decision mechanism. | H36: Validate decision gates and minimum readiness criteria. | I36: Open | J36: 2.5 | K36: Needs one decision vocabulary first (Q13).
A37: 33 | B37: Launch Readiness | C37: Cost & Risk Impact | D37: Project Budget, Spent Cost and Spent-to-Budget Ratio are displayed. Current: Cost consumption is visible. | E37: Relationship between additional mitigation cost and risk reduction is not fully evident. | F37: Show Incremental Mitigation Cost vs Risk Reduction vs Financial Exposure Avoided. | G37: Supports cost-benefit justification for mitigation spending. | H37: Validate financial impact and mitigation cost model. | I37: Open | J37: 3.3
A38: 34 | B38: Launch Readiness | C38: AI Forecast / Recommendation | D38: AI Forecast section provides a message regarding sourcing and logistics risk. Current: AI-generated insight/recommendation is displayed. | E38: Recommendation needs stronger explainability regarding why it was generated and what evidence supports it. | F38: Show Recommendation → Reason → Supporting Metrics → Expected Impact → Confidence → Suggested Action. | G38: Improves trust and usability of AI recommendations. | H38: Validate AI methodology and explainability requirements. | I38: Open | J38: 4.2 | K38: The recommendation text is authored; no model is called today (H11).
A39: 35 | B39: Launch Readiness | C39: Category Benchmark | D39: SKU performance is compared against category benchmark averages. Current: Benchmark provides a reference point. | E39: Benchmark gap may not distinguish acceptable from unacceptable performance. | F39: Introduce configurable Green / Amber / Red thresholds and business-specific benchmark rules. | G39: Enables faster identification of launch blockers. | H39: Validate benchmark thresholds with business. | I39: Open | J39: 2.5
A40: 36 | B40: Launch Readiness | C40: Launch Lifecycle | D40: Launch milestones are tracked through Go-Live. Current: The visible process focuses on readiness and launch execution. | E40: Post-launch performance feedback is not visible in the current solution. | F40: Connect launch readiness with post-launch actuals such as sales, margin, forecast accuracy, service level and launch performance. | G40: Creates a closed-loop learning process for future launches. | H40: Validate post-launch data availability and ownership. | I40: Open | J40: 3.3 | K40: Needs launch dates — 0 of 119 SKUs have one (Q3).
A41: 37 | B41: Cross-module | C41: Cross-module investigation | D41: Information exists across capabilities. | E41: Insight → Diagnosis may require manual correlation. | H41: Can users move seamlessly across Health, Profitability, Signals and Rationalization? | I41: To validate | J41: 3.7
A42: 38 | B42: Cross-module | C42: Actionability | D42: The user may see what is happening but still need to determine what to do. | E42: Insight → Recommendation → Action. | H42: Does the solution clearly guide the next business action? | I42: To validate | J42: 2.1
A43: 39 | B43: Cross-module | C43: Explainability | D43: Scores/recommendations may need clearer drivers and evidence. | E43: Score → Drivers → Root Cause → Action. | H43: Can users understand why the score/recommendation was generated? | I43: To validate | J43: 2.1
A44: 40 | B44: Cross-module | C44: Strategic SKU context | D44: Financial performance alone may not capture customer/channel/market importance. | E44: Performance → Strategic Context → Decision. | H44: What exceptions are considered before rationalization? | I44: To validate | J44: 2.5
A45: 41 | B45: Cross-module | C45: Signal-to-action | D45: Signals may require additional investigation to assess impact. | E45: Signal → Impact → Decision → Action. | H45: What happens after a signal is identified? | I45: To validate | J45: 3.6
A46: 42 | B46: Cross-module | C46: Launch decision | D46: Readiness dimensions exist; final decision criteria need validation. | E46: Assessment → GO / Conditional GO / NO-GO. | H46: Does readiness clearly support the launch decision? | I46: To validate | J46: 2.5
A47: 43 | B47: Cross-module | C47: Decision-to-impact | D47: Post-approval ownership and benefits need validation. | E47: Decision → Action → Outcome → Benefit. | H47: Can expected vs actual impact be measured? | I47: To validate | J47: 2.1
A48: 44 | B48: Cross-module | C48: Metric lineage | D48: Important metrics may require clearer definitions and traceability. | E48: Source → Calculation → Metric → Decision. | H48: Can users trace key metrics to source, logic and owner? | I48: To validate | J48: 3.1c | K48: Same root problem as H8 — fixed by one metric registry (3.1c, 3.8).

Sheet Personas & Journey
A1: Personas & Journey
A2: Sections A and B are the team's work, verbatim. Section C transcribes the team's Miro decision journey; its last column is our proposal, to confirm in M3.
A4: A · Who needs which capability
A5: Capability | B5: VP Product Management | C5: Product Manager | D5: Pricing & Margin Partner | E5: Primary decision
A6: Portfolio Health | B6: Primary | C6: Secondary | D6: Secondary | E6: Where should we invest, intervene or exit?
A7: Launch Readiness | B7: Secondary | C7: Primary | D7: Secondary | E7: Should the product launch, and what is blocking it?
A8: Profitability | B8: Primary | C8: Primary | D8: Primary | E8: Where is margin leaking and how can profitability improve?
A9: SKU Rationalization | B9: Secondary | C9: Primary | D9: Primary | E9: Which SKUs should be retained, optimized, repositioned or sunset?
A10: Signals | B10: Primary | C10: Primary | D10: Secondary | E10: What changed and what requires attention?
A11: Decision Intelligence & Orchestration | B11: Primary | C11: Primary | D11: Primary | E11: What should we do, why, what-if, who approves, and what impact will result?
A14: B · Current → future decision journey
A15: Capability | B15: Current process / pain point | C15: Future capability | D15: Future decision | E15: Business outcome
A16: Portfolio Health | B16: User investigates portfolio issues manually | C16: Detect + Diagnose + Correlate | D16: Recommendation | E16: Faster, evidence-based decision
A17: Launch Readiness | B17: Manual comparison of readiness, risk and benchmarks | C17: What-if + AI Recommendation | D17: Approval | E17: Faster and lower-risk launch decision
A18: Profitability | B18: Manual root-cause analysis across financial drivers | C18: Explainable Decision Support | D18: Corrective Action | E18: Improved margin and profitability
A19: SKU Rationalization | B19: Manual business assessment of SKU performance | C19: Scenario Comparison | D19: Retain / Optimize / Reposition / Discontinue | E19: Optimized portfolio and reduced complexity
A20: Signals | B20: User manually connects signals with portfolio evidence | C20: Prioritize + Orchestrate | D20: Action | E20: Faster response to market/customer changes
A23: C · End-to-end decision journey (team's Miro board)
A24: # | B24: Stage | C24: What happens | D24: Screens involved today | E24: Proposed home in the 5-tab target (confirm in M3)
A25: 1 | B25: Business / portfolio need | C25: A question or trigger arrives | D25: — | E25: Outside the app
A26: 2 | B26: Business inputs | C26: Data is consolidated into the solution | D26: — | E26: Data layer (warehouse + API)
A27: 3 | B27: Home | C27: The user opens the solution | D27: Home | E27: Landing summary inside Portfolio Health (Report 2)
A28: 4 | B28: User investigates | C28: Three detection paths | D28: Portfolio Health · Profitability · Signals Board | E28: Tabs: Portfolio Health, Profitability Tree, Market & VoC Signals
A29: 5 | B29: Identify problem | C29: Decision point: is there a problem? | D29: Alerts on several screens | E29: Exceptions and alerts within each tab
A30: 6 | B30: Top-Down Drill | C30: Drill into the cause | D30: Top-Down Drill | E30: A drill-down inside each tab — not a tab of its own
A31: 7 | B31: Root cause / evidence | C31: Evidence for the cause | D31: Audit drawer | E31: Audit drawer and explanation panel
A32: 8 | B32: Business assessment | C32: Evaluate the options | D32: — | E32: —
A33: 9 | B33: Decide an option | C33: Three decision paths | D33: SKU Rationalization · SKU Assortment · Launch Readiness | E33: Tabs: SKU Rationalization, Launch Readiness. Where Assortment goes is to be settled — Report 2 folds it into Portfolio Health.
A34: 10 | B34: Scenario / simulation | C34: Model the option | D34: Simulators in several tabs | E34: Simulator within the deciding tab
A35: 11 | B35: Financial / business impact | C35: Quantify it | D35: Partly | E35: Impact panel alongside the simulator
A36: 12 | B36: Decision / approval | C36: Submit and approve | D36: Approval buttons on several screens | E36: One approval flow
... A38: 14 | B38: Impact measurement | C38: Track the outcome and close | D38: Not built | E38: Closed loop — see Gap Analysis 'Action-to-impact tracking'
A40: Miro board | B40: Open the decision journey

Sheet Risks & Issues
A1: Risks & Issues
A2: Risk = might happen · Issue = already happening. Severity is a formula from Impact × Likelihood.
A4: ID | B4: Type | C4: Risk or issue | D4: Consequence | E4: Impact | F4: Likelihood | G4: Severity | H4: Owner | I4: Mitigation / next step | J4: Linked | K4: Status
A5: R1 | B5: Risk | C5: Scope unresolved — capability demo or competing product | D5: Wrong investment; rework | E5: High | F5: High | G5: =IF(OR(E5="",F5=""),"",IF((($E5="High")*3+($E5="Medium")*2+($E5="Low")*1)*(($F5="High")*3+($F5="Medium")*2+($F5="Low")*1)>=6,"High",IF((($E5="High")*3+($E5="Medium")*2+($E5="Low")*1)*(($F5="High")*3+($F5="Medium")*2+($F5="Low")*1)>=3,"Medium","Low"))) | H5: Programme owner | I5: Hold M1; proceed on default A meanwhile | J5: Q1 | K5: Open
A6: R2 | B6: Issue | C6: Conflicting figures on screen ($473M vs $851M revenue; 38.55% vs 36.2% margin) | D6: Demo credibility | E6: High | F6: High | G6: =IF(OR(E6="",F6=""),"",IF((($E6="High")*3+($E6="Medium")*2+($E6="Low")*1)*(($F6="High")*3+($F6="Medium")*2+($F6="Low")*1)>=6,"High",IF((($E6="High")*3+($E6="Medium")*2+($E6="Low")*1)*(($F6="High")*3+($F6="Medium")*2+($F6="Low")*1)>=3,"Medium","Low"))) | H6: Guna | I6: Metric registry; wire the computed arrays | J6: Q2, 3.1c | K6: Open
A7: R3 | B7: Issue | C7: Profit cards have no cost basis (no opex data) | D7: An undefendable number in front of a client | E7: High | F7: High | G7: =IF(OR(E7="",F7=""),"",IF((($E7="High")*3+($E7="Medium")*2+($E7="Low")*1)*(($F7="High")*3+($F7="Medium")*2+($F7="Low")*1)>=6,"High",IF((($E7="High")*3+($E7="Medium")*2+($E7="Low")*1)*(($F7="High")*3+($F7="Medium")*2+($F7="Low")*1)>=3,"Medium","Low"))) | I7: Remove the cards unless opex is added | J7: Q4 | K7: Open
A8: R4 | B8: Issue | C8: Two required KPIs cannot be computed (no launch dates) | D8: Brief not met | E8: High | F8: High | G8: =IF(OR(E8="",F8=""),"",IF((($E8="High")*3+($E8="Medium")*2+($E8="Low")*1)*(($F8="High")*3+($F8="Medium")*2+($F8="Low")*1)>=6,"High",IF((($E8="High")*3+($E8="Medium")*2+($E8="Low")*1)*(($F8="High")*3+($F8="Medium")*2+($F8="Low")*1)>=3,"Medium","Low"))) | I8: Synthetic launch table | J8: Q3 | K8: Open
A9: R5 | B9: Issue | C9: Real brands in demo data (seven in the database, plus PepsiCo brands) | D9: Trademark or brand complaint | E9: High | F9: Medium | G9: =IF(OR(E9="",F9=""),"",IF((($E9="High")*3+($E9="Medium")*2+($E9="Low")*1)*(($F9="High")*3+($F9="Medium")*2+($F9="Low")*1)>=6,"High",IF((($E9="High")*3+($E9="Medium")*2+($E9="Low")*1)*(($F9="High")*3+($F9="Medium")*2+($F9="Low")*1)>=3,"Medium","Low"))) | I9: Rename to fictional brands | J9: Q8, 3.1d | K9: Open
A10: R6 | B10: Issue | C10: Netherlands margin inverted against the source | D10: Credibility with an informed viewer | E10: Medium | F10: Medium | G10: =IF(OR(E10="",F10=""),"",IF((($E10="High")*3+($E10="Medium")*2+($E10="Low")*1)*(($F10="High")*3+($F10="Medium")*2+($F10="Low")*1)>=6,"High",IF((($E10="High")*3+($E10="Medium")*2+($E10="Low")*1)*(($F10="High")*3+($F10="Medium")*2+($F10="Low")*1)>=3,"Medium","Low"))) | I10: Generator constraint plus a validation check | J10: Q6 | K10: Open
A11: R7 | B11: Risk | C11: Database password in pushed git history (a3a3c54) | D11: Credential exposure | E11: Medium | F11: Low | G11: =IF(OR(E11="",F11=""),"",IF((($E11="High")*3+($E11="Medium")*2+($E11="Low")*1)*(($F11="High")*3+($F11="Medium")*2+($F11="Low")*1)>=6,"High",IF((($E11="High")*3+($E11="Medium")*2+($E11="Low")*1)*(($F11="High")*3+($F11="Medium")*2+($F11="Low")*1)>=3,"Medium","Low"))) | H11: Guna | I11: Rotated; never reuse; confirm repository visibility | J11: Q12 | K11: Mitigated
A12: R8 | B12: Issue | C12: Local PostgreSQL accepts connections without a password ('trust') | D12: Any local user can connect as superuser | E12: Low | F12: Medium | G12: =IF(OR(E12="",F12=""),"",IF((($E12="High")*3+($E12="Medium")*2+($E12="Low")*1)*(($F12="High")*3+($F12="Medium")*2+($F12="Low")*1)>=6,"High",IF((($E12="High")*3+($E12="Medium")*2+($E12="Low")*1)*(($F12="High")*3+($F12="Medium")*2+($F12="Low")*1)>=3,"Medium","Low"))) | H12: Guna | I12: Switch to scram-sha-256, then strengthen the app password | J12: — | K12: Open
A13: R9 | B13: Risk | C13: No demo date set | D13: No forcing function; scope drifts | E13: High | F13: Medium | G13: =IF(OR(E13="",F13=""),"",IF((($E13="High")*3+($E13="Medium")*2+($E13="Low")*1)*(($F13="High")*3+($F13="Medium")*2+($F13="Low")*1)>=6,"High",IF((($E13="High")*3+($E13="Medium")*2+($E13="Low")*1)*(($F13="High")*3+($F13="Medium")*2+($F13="Low")*1)>=3,"Medium","Low"))) | H13: Programme owner | I13: Set a date in M1 | J13: Q9 | K13: Open
A14: R10 | B14: Risk | C14: Backend (6 weeks) is the critical path | D14: Demo slips | E14: High | F14: Medium | G14: =IF(OR(E14="",F14=""),"",IF((($E14="High")*3+($E14="Medium")*2+($E14="Low")*1)*(($F14="High")*3+($F14="Medium")*2+($F14="Low")*1)>=6,"High",IF((($E14="High")*3+($E14="Medium")*2+($E14="Low")*1)*(($F14="High")*3+($F14="Medium")*2+($F14="Low")*1)>=3,"Medium","Low"))) | I14: Narrow the API to Next-state endpoints; start once the KPI framework is agreed | J14: 3.8 | K14: Open
A15: R11 | B15: Risk | C15: Knowledge concentrated in one contributor — all commits since 1 Sep | D15: Single point of failure | E15: Medium | F15: Medium | G15: =IF(OR(E15="",F15=""),"",IF((($E15="High")*3+($E15="Medium")*2+($E15="Low")*1)*(($F15="High")*3+($F15="Medium")*2+($F15="Low")*1)>=6,"High",IF((($E15="High")*3+($E15="Medium")*2+($E15="Low")*1)*(($F15="High")*3+($F15="Medium")*2+($F15="Low")*1)>=3,"Medium","Low"))) | I15: CLAUDE.md, this tracker, pairing | J15: — | K15: Open
A16: R12 | B16: Risk | C16: Work tracker and architecture diagrams not in version control (gitignored) | D16: Lost on a fresh clone | E16: Medium | F16: Medium | G16: =IF(OR(E16="",F16=""),"",IF((($E16="High")*3+($E16="Medium")*2+($E16="Low")*1)*(($F16="High")*3+($F16="Medium")*2+($F16="Low")*1)>=6,"High",IF((($E16="High")*3+($E16="Medium")*2+($E16="Low")*1)*(($F16="High")*3+($F16="Medium")*2+($F16="Low")*1)>=3,"Medium","Low"))) | H16: Guna | I16: Remove from .gitignore; use this sheet as the shared tracker | J16: — | K16: Open
A17: R13 | B17: Risk | C17: About 30 files of completed work are uncommitted | D17: Loss of work | E17: High | F17: Low | G17: =IF(OR(E17="",F17=""),"",IF((($E17="High")*3+($E17="Medium")*2+($E17="Low")*1)*(($F17="High")*3+($F17="Medium")*2+($F17="Low")*1)>=6,"High",IF((($E17="High")*3+($E17="Medium")*2+($E17="Low")*1)*(($F17="High")*3+($F17="Medium")*2+($F17="Low")*1)>=3,"Medium","Low"))) | H17: Guna | I17: Commit in logical chunks (do not push until R7 is closed) | J17: — | K17: Open
A18: R14 | B18: Issue | C18: Smoke test covers 9 of 12 tabs | D18: Breakage in tabs 9–11 goes unnoticed | E18: Medium | F18: Medium | G18: =IF(OR(E18="",F18=""),"",IF((($E18="High")*3+($E18="Medium")*2+($E18="Low")*1)*(($F18="High")*3+($F18="Medium")*2+($F18="Low")*1)>=6,"High",IF((($E18="High")*3+($E18="Medium")*2+($E18="Low")*1)*(($F18="High")*3+($F18="Medium")*2+($F18="Low")*1)>=3,"Medium","Low"))) | I18: Extend the test to all tabs | J18: 4.3 | K18: Open
A19: R15 | B19: Risk | C19: LLM model and pricing assumptions are out of date | D19: Wrong running cost quoted | E19: Medium | F19: Medium | G19: =IF(OR(E19="",F19=""),"",IF((($E19="High")*3+($E19="Medium")*2+($E19="Low")*1)*(($F19="High")*3+($F19="Medium")*2+($F19="Low")*1)>=6,"High",IF((($E19="High")*3+($E19="Medium")*2+($E19="Low")*1)*(($F19="High")*3+($F19="Medium")*2+($F19="Low")*1)>=3,"Medium","Low"))) | I19: Re-price before quoting | J19: Q10 | K19: Open
A20: R16 | B20: Issue | C20: Stale documentation — SKU counts disagree across documents | D20: Wrong numbers repeated | E20: Low | F20: High | G20: =IF(OR(E20="",F20=""),"",IF((($E20="High")*3+($E20="Medium")*2+($E20="Low")*1)*(($F20="High")*3+($F20="Medium")*2+($F20="Low")*1)>=6,"High",IF((($E20="High")*3+($E20="Medium")*2+($E20="Low")*1)*(($F20="High")*3+($F20="Medium")*2+($F20="Low")*1)>=3,"Medium","Low"))) | I20: Correct the documents; treat them as dated | J20: — | K20: Open
A21: R17 | B21: Issue | C21: Six npm security advisories in build tooling | D21: Development-only exposure | E21: Low | F21: Low | G21: =IF(OR(E21="",F21=""),"",IF((($E21="High")*3+($E21="Medium")*2+($E21="Low")*1)*(($F21="High")*3+($F21="Medium")*2+($F21="Low")*1)>=6,"High",IF((($E21="High")*3+($E21="Medium")*2+($E21="Low")*1)*(($F21="High")*3+($F21="Medium")*2+($F21="Low")*1)>=3,"Medium","Low"))) | I21: Apply non-breaking npm audit fixes | J21: — | K21: Open
A22: R18 | B22: Issue | C22: Lifecycle 'Total Revenue' shows ~$10,592M — about 22× actual net sales | D22: Executives see a revenue figure an order of magnitude too high | E22: High | F22: High | G22: =IF(OR(E22="",F22=""),"",IF((($E22="High")*3+($E22="Medium")*2+($E22="Low")*1)*(($F22="High")*3+($F22="Medium")*2+($F22="Low")*1)>=6,"High",IF((($E22="High")*3+($E22="Medium")*2+($E22="Low")*1)*(($F22="High")*3+($F22="Medium")*2+($F22="Low")*1)>=3,"Medium","Low"))) | H22: Guna | I22: Fix LifecycleHealthPanel.tsx:100; route through the metric registry. Found by the team's review. | J22: 3.1c | K22: Open
A23: R19 | B23: Issue | C23: Five competing project plans across the team | D23: People track against different lists; status disagrees | E23: Medium | F23: High | G23: =IF(OR(E23="",F23=""),"",IF((($E23="High")*3+($E23="Medium")*2+($E23="Low")*1)*(($F23="High")*3+($F23="Medium")*2+($F23="Low")*1)>=6,"High",IF((($E23="High")*3+($E23="Medium")*2+($E23="Low")*1)*(($F23="High")*3+($F23="Medium")*2+($F23="Low")*1)>=3,"Medium","Low"))) | I23: Adopt this merged tracker (M8); retire the others | J23: D13 | K23: Open
A24: R20 | B24: Issue | C24: Team benchmark compares PLM vendors with mixed scales; sources unverified | D24: Weak external comparison | E24: Low | F24: Medium | G24: =IF(OR(E24="",F24=""),"",IF((($E24="High")*3+($E24="Medium")*2+($E24="Low")*1)*(($F24="High")*3+($F24="Medium")*2+($F24="Low")*1)>=6,"High",IF((($E24="High")*3+($E24="Medium")*2+($E24="Low")*1)*(($F24="High")*3+($F24="Medium")*2+($F24="Low")*1)>=3,"Medium","Low"))) | I24: Use Report 3 externally; verify sources; one rating scale | J24: 1.5 | K24: Open
A25: R21 | B25: Risk | C25: Tab rework (3.2–3.6) has no estimates | D25: Gate 3 and the demo date are optimistic | E25: Medium | F25: High | G25: =IF(OR(E25="",F25=""),"",IF((($E25="High")*3+($E25="Medium")*2+($E25="Low")*1)*(($F25="High")*3+($F25="Medium")*2+($F25="Low")*1)>=6,"High",IF((($E25="High")*3+($E25="Medium")*2+($E25="Low")*1)*(($F25="High")*3+($F25="Medium")*2+($F25="Low")*1)>=3,"Medium","Low"))) | I25: Estimate from the gap analyses in M8 | J25: 3.2–3.6 | K25: Open
A26: R22 | B26: Issue | C26: Timeline selector fabricates variance on every figure, including the two KPI-strip metrics previously found to be genuinely computed | D26: Changing the date-range filter changes numbers for reasons unrelated to the real period -- including '$473M', which is perturbed by a deterministic hash even at the default 12-month view | E26: High | F26: High | G26: =IF(OR(E26="",F26=""),"",IF((($E26="High")*3+($E26="Medium")*2+($E26="Low")*1)*(($F26="High")*3+($F26="Medium")*2+($F26="Low")*1)>=6,"High",IF((($E26="High")*3+($E26="Medium")*2+($E26="Low")*1)*(($F26="High")*3+($F26="Medium")*2+($F26="Low")*1)>=3,"Medium","Low"))) | H26: Guna | I26: Remove the noise layer (utils/timeframe.ts) once the metric registry (3.1c) is the single source; until then, treat every displayed figure as unverified whenever the timeline filter is not left at its default | J26: 3.1c | K26: Open

Sheet Decisions
A1: Decisions — already made
A2: Add new decisions as they are taken, including answers from Open Questions.
A4: # | B4: Date | C4: Decision | D4: Why | E4: Alternatives considered | F4: Decided by | G4: Revisit if
A5: D1 | B5: ~9 Sep 2026 | C5: Build a synthetic dataset | D5: No transaction-level data was available — only aggregate findings. | E5: Wait for real data; keep hardcoded figures | F5: Project team | G5: Real client extracts become available
A6: D2 | B6: By 14 Sep 2026 | C6: Report in US dollars only | D6: Simplicity; European figures treated as already converted. | E6: Multi-currency with an FX table | F6: Guna | G6: A client needs local currency
A7: D3 | B7: 14 Sep 2026 | C7: PostgreSQL star schema of 13 tables | D7: Relational integrity and metrics in SQL. | E7: S3 + Parquet + DuckDB (earlier proposal) | F7: Project team | G7: Analytics outgrow PostgreSQL
A8: D4 | B8: ~14 Sep 2026 | C8: Do not force the 34/16/16/34 segment split | D8: With median splits on both axes it is mathematically unreachable. | E8: Bias the generator | F8: Project team | G8: —
A9: D5 | B9: 17 Sep 2026 | C9: Target five domain tabs | D9: The Lab 8 brief requires exactly five. | E9: Keep 12 | F9: Brief (binding) | G9: —
A10: D6 | B10: 20 Sep 2026 | C10: Backend in Python / FastAPI | D10: The data layer is already Python. | E10: Node / Express | F10: Guna | G10: —
A11: D7 | B11: 20 Sep 2026 | C11: Delete the unused Express server and dependencies | D11: Nothing used them; contradicted D6. | E11: Keep as an API seed | F11: Guna | G11: —
A12: D8 | B12: 20 Sep 2026 | C12: Compute metrics in SQL — one implementation | D12: Copies of a formula drift apart. | E12: Compute in the API | F12: Project team | G12: —
A13: D9 | B13: 20 Sep 2026 | C13: The LLM explains results; it never does arithmetic | D13: Lower cost; reproducible numbers. | E13: Let the LLM compute | F13: Project team — to confirm (Q10) | G13: —
A14: D10 | B14: 20 Sep 2026 | C14: Pin Python dependencies exactly | D14: The generator is deterministic. | E14: Version ranges | F14: Project team | G14: —
A15: D11 | B15: 20 Sep 2026 | C15: Non-superuser application database role | D15: Least privilege. | E15: Connect as postgres | F15: Guna | G15: —
... A18: D14 | B18: 22 Sep 2026 | C18: Assume no deadline; keep every date tentative and computed from durations | D18: No deadline is set (confirmed 22 Sep); the 20-day figure is a placeholder. | E18: Plan to 30 Sep | F18: Guna | G18: A demo date is set (Q9)

Sheet Architecture Roadmap
A1: Architecture Roadmap — from today to the target
A2: Diagrams: documentation/system_architecture.md (Excalidraw-ready; not in git — see R12).
A4: Sequence
A5: Step | B5: Change | C5: Why in this order | D5: Plan step | F5: Status
A6: 1 | B6: Load the dataset into PostgreSQL | C6: Everything else reads from it. | D6: 3.1a | F6: Done
A7: 2 | B7: Settle the baseline, KPI list and decision vocabulary (M2) | C7: Registry and rules need one definition. | D7: 1.7 | F7: Not started
A8: 3 | B8: Derived metrics and the 16 checks in SQL | C8: One implementation per formula. | D8: 3.1b | F8: Not started
A9: 4 | B9: Metric registry — one definition per figure | C9: Structural fix for conflicting numbers. | D9: 3.1c | F9: Not started
A10: 5 | B10: Wire the five unused computed arrays; fix the lifecycle revenue bug | C10: Quick wins; no backend needed. | D10: 3.1c | F10: Not started
A11: 6 | B11: FastAPI read endpoints over the registry | C11: Makes the database reachable. | D11: 3.8 | F11: Not started
A12: 7 | B12: One data hook in React; replace constant imports | C12: A data swap, not a rewrite. | D12: 3.9 | F12: Not started
A13: 8 | B13: Consolidate 12 tabs into 5, following the decision journey | C13: Brief compliance. | D13: 3.7 | F13: Not started
A14: 9 | B14: Checks and smoke test in CI, all 12 tabs | C14: Catches regressions. | D14: 4.3 | F14: Not started
A15: 10 | B15: Closed loop: decision → action → measured impact | C15: The journey's final stage; not built. | D15: 2.1, 4.8 | F15: Not started
A16: 11 | B16: Future: scheduled ingestion from ERP, POS, PLM, demand planning | C16: Real data replaces synthetic. | D16: 4.8 | F16: Not started
A17: 12 | B17: Future: orchestrator and five agents — the LLM explains, never computes | C17: The AgenticBus proper. | D17: 4.1, 4.2 | F17: Not started
A19: Component view — Now → Next → Future
B20: Component | C20: Now | D20: Next (trustworthy demo) | E20: Future (target) | F20: Plan step
B21: Source of figures | C21: Compiled into the bundle; 2 of 7 computed arrays wired | D21: PostgreSQL + metric registry | E21: Same, fed by real extracts | F21: 3.1c, 3.8, 3.9
B22: API | C22: None | D22: FastAPI read API | E22: FastAPI gateway | F22: 3.8
B23: Tabs | C23: 12 | D23: Consolidating to 5 | E23: 5 domain tabs | F23: 3.7
B24: Decision loop | C24: Stops at approval buttons | D24: Approve → act | E24: Act → measure impact → learn | F24: 2.1, 4.8
B25: Agents | C25: Keyword matching | D25: Unchanged | E25: Orchestrator + 5 agents | F25: 4.1, 4.2
B26: LLM | C26: None | D26: None | E26: Explanation only, never arithmetic | F26: 4.2
B27: Checks | C27: 16 data checks; smoke on 9 of 12 tabs | D27: Both in CI; all tabs | E27: Plus data-quality gates | F27: 4.3
B28: Hosting | C28: Static frontend on Vercel | D28: Plus API and database hosting | E28: Production hosting | F28: 4.7

Sheet Research & Data
A1: Research & Data — what we learned
A2: Our research and the team's, side by side. Light yellow = please complete.
A4: # | B4: Item | C4: Question it answered | D4: What we found | E4: What it changed | F4: Link
A5: R1 | B5: KT on the existing application | C5: What does the app do, for whom, from what data? | D5: 3 personas, 12 tabs, 43 overlays; every figure hardcoded; no backend or database. | E5: Remediation before new features.
A6: R2 | B6: Project blueprint and brief | C6: What does the brief require? | D6: Exactly 5 domain tabs, 6 required KPIs, 3 role lenses. Labs are GTM assets. | E6: Defined the target state.
A7: R3 | B7: Report 1 · Metric Dictionary | C7: What does every number mean? | D7: 2 of 6 required KPIs computed; revenue and margin each have two baselines. | E7: Metric integrity (3.1c); Q2–Q5. | F7: Report 1 (Google Doc)
A8: R4 | B8: Report 2 · Twelve Tabs to Five | C8: Is every tab worth keeping, per persona? | D8: 12 tabs vs 5 required; duplicated persona views; PM may see the VP's launch view. | E8: Consolidation (3.7); Q7. | F8: Report 2 (Google Doc)
A9: R5 | B9: Report 3 · Worth Building? | C9: Who are the incumbents? | D9: Depends on positioning. Competing on data breadth is not winnable; on explainability it is. | E9: Q1. | F9: Report 3 (Google Doc)
A10: R6 | B10: Team review · Portfolio Health | C10: Does Portfolio Health support executive decisions? | D10: 21 gaps: KPI hierarchy and targets, unexplained health score, no stage-specific actions, revenue that does not reconcile (Critical), no what-if, no closed loop. | E10: Requirements for 3.2; reconciliation → 3.1c. | F10: Gap Analysis tab
A11: R7 | B11: Team review · Launch Readiness | C11: Does Launch Readiness support a launch decision? | D11: 15 gaps: a score without drivers, no GO / CONDITIONAL GO / NO-GO, milestones without dependencies, no multi-scenario comparison, no post-launch loop. | E11: Requirements for 3.3; decision rule → 2.5, Q13. | F11: Gap Analysis tab
A12: R8 | B12: Team · Persona × capability matrix | C12: Who is primary for which decision? | D12: VP primary for Portfolio Health, Profitability, Signals. PM primary for Launch Readiness, Profitability, SKU Rationalization, Signals. Pricing & Margin primary for Profitability and SKU Rationalization. | E12: Evidence for Q7; the PM should get its own launch view. | F12: Personas & Journey tab
A13: R9 | B13: Team · End-to-end decision journey | C13: How does a user move from signal to decision? | D13: Detect → diagnose (drill, root cause) → decide (Rationalization, Assortment, Launch) → simulate → approve → act → measure. | E13: Demo script (4.5); consolidation logic (3.7). | F13: Personas & Journey tab
A14: R10 | B14: Team · PLM benchmark | C14: How does the product compare with PLM and portfolio tools? | D14: Five vendors; differentiation claimed in SKU rationalization, assortment and market signals. | E14: Complements Report 3; needs verified sources before external use. | F14: Benchmark tab
A15: R11 | B15: Dataset search | C15: Is there a transaction-level dataset we can use? | D15: No — only aggregate outputs of a notebook analysis. | E15: Generate our own (D1).
A16: R12 | B16: Other data sources reviewed | C16: What else did we look at, and why did it fall short?
A17: R13 | B17: Synthetic dataset | C17: Can we reproduce the known findings? | D17: 119 SKUs × 7 countries × 4 channels × 731 days; 368,013 rows; seeded (20260909). | E17: A real data spine.
A18: R14 | B18: Validation | C18: Does it match the source? | D18: 16 of 16 targets met: $473.0M net sales, +8.29% growth, 38.55% margin — confirmed after loading. | E18: Confidence.
A19: R15 | B19: Known data gaps | C19: What can the data not support yet? | D19: No launch dates (0 of 119); no opex; Netherlands margin inverted; no competitor or VoC feed. | E19: Q3, Q4, Q6, Q11.

Sheet Handover Findings
A1: Handover Findings — the condition of what we received
A2: Measured, not estimated. Doubles as the agenda for reverse KT (M5).
A4: # | B4: Area | C4: What we found | D4: Evidence | E4: Why it mattered | F4: What we did | G4: Status
A5: H1 | B5: Repository hygiene | C5: 144 tracked files in the root — scratch scripts, text dumps, duplicated HTML and PDF — plus .gemini/ (38) and extracted_tabs/ (6). | D5: git ls-files | E5: Hard to tell product code from debris. | F5: 187 files removed; the root holds 10 tracked files. | G5: Done
A6: H2 | B6: Oversized files | C6: Nine component files totalling 22,619 lines; the largest 3,981. | D6: Line counts | E6: Slow to change and easy to break. | F6: Split into 30 modules, 11,854 lines (−47%). | G6: Done
A7: H3 | B7: Dead code | C7: About 3,500 lines never executed, including PortfolioHealthMapOld (1,289) and 10 orphaned components. | D7: Import graph | E7: Misled an early audit of what each persona sees. | F7: Removed. | G7: Done
A8: H4 | B8: Styling defects | C8: 1,237 invalid Tailwind colour classes across 63 files. | D8: Commit, 1 Sep | E8: Colours silently not applied. | F8: Fixed. | G8: Done
A9: H5 | B9: Type safety | C9: Type checking had been bypassed. | D9: Commit, 1 Sep | E9: Errors surfaced only at runtime. | F9: Restored. | G9: Done
A10: H6 | B10: No data layer | C10: No dataset, database or API; every figure hardcoded. | D10: Zero network calls in src/ | E10: Numbers could not be audited or refreshed. | F10: Dataset generated and loaded; API not yet built. | G10: In progress
A11: H7 | B11: Missing source data | C11: Original figures came from a notebook analysis; no transaction-level data was handed over. | D11: Comments in data.ts | E11: Metrics could not be computed or checked. | F11: Built a calibrated synthetic dataset. | G11: Done
A12: H8 | B12: Conflicting figures | C12: Revenue $473M vs $851M; margin 38.55% vs 36.2%; rationalize candidates 46 vs 35; tail risk 15.79% vs 27.08%. | D12: Report 1 | E12: Undermines credibility in a demo. | F12: Diagnosed; fix planned (3.1c). | G12: Open
A13: H9 | B13: Designed but empty metrics | C13: 20 metric labels styled; only 8 have a value. | D13: KPICard.tsx vs data.ts | E13: Empty KPI strips on four tabs. | F13: Planned (3.1c). | G13: Open
A14: H10 | B14: Navigation overload | C14: 12 tabs against a brief requiring 5; VP and standard duplicates. | D14: Report 2 | E14: Brief not met. | F14: Consolidation planned (3.7). | G14: Open
A15: H11 | B15: Simulated AI | C15: The agent widget matches keywords and simulates typing. | D15: Agent widget code | E15: The demo implies AI it does not perform. | F15: Planned (4.2). | G15: Open
... A19: H15 | B19: Revenue units bug | C19: The lifecycle panel sums each SKU's 'rev' field and labels it $M: ~$10,592M against $473M actual. | D19: LifecycleHealthPanel.tsx:100 — found by the team's review | E19: Executives see revenue about 22× too high. | F19: Confirmed 22 Sep; fix planned (3.1c). | G19: Open

Sheet Timeline
A1: Timeline — from handover to today
A2: Reconstructed from git history and project files. Light yellow = please confirm.
A4: When | B4: Stage | C4: Event | D4: Detail | E4: Source
A5: 18 May 2026 | B5: Build — previous team | C5: Repository started | D5: First commit by acies-Jai. | E5: git log
A6: 18 May – 27 Jul 2026 | B6: Build — previous team | C6: Application built | D6: 369 commits from four contributors: Amita (149), SreeVyshnavi (143), acies-Jai (72), Jaiadithya A (5). | E6: git log
A7: 16 Jun 2026 | B7: Build — previous team | C7: A replaced view is left in the code | D7: PortfolioHealthMapOld becomes unreachable but stays in a live file — 1,289 dead lines until 20 Sep. | E7: Code history
A8: 22 Jun 2026 | B8: Build — previous team | C8: Figures switched to US dollars | D8: 'Currency conversion to dollars' (Amita). | E8: git log
A9: 13 Jul 2026 | B9: Build — previous team | C9: Real brands added to the SKU list | D9: Sprite, Coca-Cola, Thums Up, 'Foorti', Pulpy Orange, 5-Star and Munch in one commit. | E9: git log
A10: 24 Jul 2026 | B10: Build — previous team | C10: Competitor tracker and PricingAI console | D10: Adds a Pepsi / Mountain Dew price-elasticity simulator to the Signals Board. | E10: git log
A11: 27 Jul 2026 | B11: Handover | C11: Last commit by the previous team | D11: — | E11: git log
A12: 27 Jul – 1 Sep 2026 | B12: Handover | C12: Repository idle | D12: No commits for five weeks. | E12: git log
B13: KT | C13: One week of knowledge transfer | D13: Enter the dates in column A. | E13: Confirm
A14: 1 Sep 2026 | B14: Remediation | C14: Current team's first commits | D14: Type checking restored; bundle split; 1,237 invalid colour classes fixed; 43 overlays moved onto shared components. | E14: 3 commits
A15: 3 Sep 2026 | B15: Initiation | C15: Project start (per team tracker) | D15: Team tracker records 20 planned working days — a placeholder. | E15: Team tracker
A16: ~9 Sep 2026 | B16: Data | C16: Dataset search comes up short | D16: Only aggregate outputs of a notebook analysis were available. Decision to generate our own (D1). | E16: Research & Data tab
A17: 14 Sep 2026 | B17: Data | C17: Synthetic dataset generated and validated | D17: 119 SKUs, 368,013 fact rows, 16 of 16 targets met. | E17: Commit a3a3c54
A18: 17 Sep 2026 | B18: Research | C18: Three feasibility reports published | D18: Metric Dictionary · Twelve Tabs to Five · Worth Building? | E18: Links tab
A19: 20 Sep 2026 | B19: Remediation | C19: Codebase clean-up completed | D19: 187 files removed; nine oversized files split into 30 modules; Express server and 124 npm packages removed. | E19: TODO.md
A20: 20 Sep 2026 | B20: Architecture | C20: Current → target architecture drawn | D20: Backend confirmed as Python / FastAPI. | E20: system_architecture.md
A21: 20 Sep 2026 | B21: Data | C21: PostgreSQL warehouse live | D21: 377,364 rows; reconciles to $473.0M, +8.29%, 38.55%. | E21: Research & Data tab
A22: 21 Sep 2026 | B22: Alignment | C22: Stakeholder questions drafted | D22: 12 open questions, each with a recommendation and a default. | E22: documentation/pitch.md
A23: 22 Sep 2026 | B23: Tracking | C23: Team tracker reviewed; plans merged | D23: The team's P1–P4 plan, gap analyses and persona work merged into this tracker. Lifecycle revenue bug confirmed. Deadline confirmed as not yet set. | E23: This tracker
A24: 23 Sep 2026 | B24: Frontend | C24: Persona-specific sidebar ordering prototyped | D24: Sidebar order now differs per role, sourced from the persona matrix; verified on all three roles by screenshot. Found and logged a real bug: role does not update from a hashchange after first load. Not committed. | E24: App.tsx; TODO.md O10
A25: 23 Sep 2026 | B25: Metric integrity | C25: Every formula in the app catalogued | D25: Python generator, SQL, and all 9 frontend tabs -- each formula marked real / real-formula-fake-input / fabricated. New finding: the timeline selector fabricates variance on every figure, including the two KPI-strip metrics previously thought genuinely computed. | E25: documentation/formulas.md

Sheet Benchmark
A1: Competitive Benchmark — PLM / PPM vendors (team research)
A2: Carried verbatim. Complements Report 3, which compares against FMCG intelligence vendors. Read the caveats before using it outside the team.
A4: Capability | B4: Our product | C4: Planview | D4: Oracle PLM | E4: SAP PLM | F4: Siemens Teamcenter | G4: Salsify
A5: Product lifecycle | B5: ✅ | C5: ✅ | D5: ✅ | E5: ✅ | F5: Strong | G5: Partial
A6: Portfolio health | B6: Strong potential | C6: Strong | D6: ✅ | E6: ✅ | F6: Partial | G6: Partial
A7: Product launch | B7: Strong | C7: Strong | D7: Strong | E7: ✅ | F7: ✅ | G7: Strong
A8: Profitability | B8: Strong potential | C8: ✅ | D8: ✅ | E8: Strong | F8: ✅ | G8: Limited
A9: SKU rationalization | B9: Core | C9: Partial | D9: Partial | E9: Partial | F9: Partial | G9: Partial
A10: SKU assortment | B10: Core | C10: Partial | D10: Partial | E10: Partial | F10: Partial | G10: Strong-ish
A11: Scenario simulation | B11: Existing | C11: Strong | D11: ✅ | E11: Strong in costing | F11: Partial | G11: Partial
A12: Market/VoC signals | B12: Core | C12: Partial | D12: Partial | E12: Partial | F12: Partial | G12: Strong for digital shelf
A13: AI recommendations | B13: Agent Orchestrator | C13: AI | D13: AI | E13: AI | F13: AI | G13: AI
A14: Executive decision cockpit | B14: Strong potential | C14: Strong | D14: Strong | E14: Strong | F14: Partial | G14: Partial
A15: Supply-chain integration | B15: Potential differentiator | C15: Partial | D15: Strong | E15: Strong | F15: Strong | G15: Integration
A16: Engineering/PLM depth | B16: Limited | C16: Limited | D16: Strong | E16: Strong | F16: Very strong | G16: Limited
A18: Caveats
A19: • | B19: Full PLM engineering is out of scope for this product (Overview → Scope), yet four of the five comparators are PLM systems.
A20: • | B20: Our product is rated on potential ('Strong potential', 'Core'); competitors on current capability — not like-for-like.
A21: • | B21: Three rating scales are mixed (✅ / Strong / Partial). The 'AI recommendations' row reads 'AI' for everyone.
A22: • | B22: Sources are vendor product pages. The Planview link points to Oracle's PLM page; Salsify has no source.
A24: Positioning (team's diagram)
A25: Product lifecycle | B25: PLM (Siemens Teamcenter, SAP PLM, Oracle PLM) and portfolio management (Planview, Oracle) → Product Lifecycle & Portfolio Intelligence → Portfolio Health · Profitability · SKU Rationalization · Launch Readiness · Cost / Risk · SKU Assortment → Signals / AI agents → Decision / recommendation.

Sheet Links
A1: Links — every document, repository and the live demo
A2: 'In git?' matters: an untracked or gitignored file is lost on a fresh clone.
A4: Document | B4: What it covers | C4: Date | D4: Link / location | E4: Also at | F4: In git?
A5: Report 1 · Metric Dictionary | B5: Every metric defined | C5: 17 Sep 2026 | D5: Google Doc | E5: Artifact | F5: No
A6: Report 2 · Twelve Tabs to Five | B6: Per-persona tab audit | C6: 17 Sep 2026 | D6: Google Doc | E6: Artifact | F6: No
A7: Report 3 · Worth Building? | B7: Competitive landscape | C7: 17 Sep 2026 | D7: Google Doc | E7: Artifact | F7: No
A8: Reports folder | B8: Acies Portfolio Lab — Reports | C8: — | D8: Google Drive folder | F8: No
A9: Team tracker | B9: Source of P1–P4, gap analyses, persona matrix, benchmark | C9: 22 Sep 2026 | D9: Research_doc/Product_Lifecycle_Portfolio_Intelligence_Project_Tracker 1.xlsx | F9: Not yet committed
A10: Decision journey (Miro) | B10: End-to-end user decision flow | C10: — | D10: Miro board | F10: —
A11: Build brief | B11: What exists, tech stack | C11: Sep 2026 | D11: Artifact | F11: No
A12: Data model | B12: Tables, columns, keys | C12: Sep 2026 | D12: Artifact | F12: No
A13: Validation | B13: Dataset validation results | C13: Sep 2026 | D13: Artifact | F13: No
A14: Stakeholder pitch | B14: Reports and open questions | C14: 21 Sep 2026 | D14: documentation/pitch.md | F14: Not yet committed
A15: System architecture | B15: Now / Next / Future diagrams | C15: 20 Sep 2026 | D15: documentation/system_architecture.md | F15: Gitignored
A16: Data model specification | B16: 13 tables, types, keys | C16: 14 Sep 2026 | D16: documentation/data_model_specification.md | F16: Yes
A17: Project blueprint | B17: Original research brief | C17: — | D17: Research_doc/Acies AgenticBus_ Product Lifecycle and Portfolio Intelligence Project Blueprint.docx | F17: Yes
A18: CLAUDE.md | B18: Guidance for AI-assisted development | C18: 20 Sep 2026 | D18: CLAUDE.md | F18: Not yet committed
A19: TODO.md | B19: Engineering work log | C19: Live | D19: TODO.md | F19: Gitignored
... A22: Repository (upstream) | B22: Previous team's repository | C22: Live | D22: GitHub | F22: —
